Workbook
Name Slicer_Gender: #N/A
Name Slicer_Payment_Type: #N/A
Name Slicer_Region: #N/A
Name Slicer_Years__Order_Date: #N/A

Sheet Customer_Dim
A1: Customer_ID | B1: Customer_ID | C1: Name | D1: Age | E1: Gender | F1: City | G1: State | H1: Country | I1: Loyalty_Level
A2: CUST1000 | B2: CUST1000 | C2: Sheena Bonilla | D2: 26 | E2: Female | F2: Donaldton | G2: North Carolina | H2: USA | I2: Platinum
A3: CUST1001 | B3: CUST1001 | C3: Eugene Nelson | D3: 29 | E3: Female | F3: Phillipsmouth | G3: North Dakota | H3: USA | I3: Platinum
A4: CUST1002 | B4: CUST1002 | C4: Dr. Benjamin Price | D4: 59 | E4: Female | F4: Kylebury | G4: Alabama | H4: USA | I4: Platinum
A5: CUST1003 | B5: CUST1003 | C5: Jeremy Harris | D5: 64 | E5: Female | F5: Thomastown | G5: Ohio | H5: USA | I5: Bronze
A6: CUST1004 | B6: CUST1004 | C6: Caroline Collins | D6: 24 | E6: Male | F6: Nicholasshire | G6: California | H6: USA | I6: Silver
A7: CUST1005 | B7: CUST1005 | C7: Christine Vaughn | D7: 29 | E7: Female | F7: East Amandamouth | G7: Oregon | H7: USA | I7: Bronze
A8: CUST1006 | B8: CUST1006 | C8: Amber Jackson | D8: 29 | E8: Female | F8: Deborahborough | G8: South Dakota | H8: USA | I8: Platinum
A9: CUST1007 | B9: CUST1007 | C9: Daniel Boyd | D9: 53 | E9: Female | F9: West Pamelafurt | G9: West Virginia | H9: USA | I9: Bronze
A10: CUST1008 | B10: CUST1008 | C10: Melissa Howard | D10: 64 | E10: Male | F10: Maynardton | G10: New Hampshire | H10: USA | I10: Gold
A11: CUST1009 | B11: CUST1009 | C11: Ms. Maria Leach | D11: 53 | E11: Male | F11: Melissashire | G11: Pennsylvania | H11: USA | I11: Platinum
A12: CUST1010 | B12: CUST1010 | C12: Dominic Page | D12: 28 | E12: Female | F12: Port Michaelburgh | G12: Pennsylvania | H12: USA | I12: Bronze
A13: CUST1011 | B13: CUST1011 | C13: Brian Lopez | D13: 55 | E13: Female | F13: East Krista | G13: New York | H13: USA | I13: Gold
... A501: CUST1499 | B501: CUST1499 | C501: Philip Pennington | D501: 27 | E501: Female | F501: East Valerieview | G501: Oregon | H501: USA | I501: Platinum

Sheet Product_Dim
A1: Product_ID | B1: Product_Name | C1: Category | D1: Sub_Category | E1: Brand | F1: Cost | G1: Stock
A2: PROD0 | B2: Brother Laser Printer | C2: Electronics | D2: Computer | E2: Hunt Inc | F2: 112.42 | G2: 416
A3: PROD1 | B3: Men's Graphic T-Shirt | C3: Clothing | D3: Tops | E3: Terry-Moore | F3: 342.56 | G3: 181
A4: PROD2 | B4: Women's Casual Hoodie | C4: Clothing | D4: Outerwear | E4: Sims Inc | F4: 254.62087 | G4: 352
A5: PROD3 | B5: Men's Running Jacket | C5: Clothing | D5: Outerwear | E5: Pineda Ltd | F5: 364.67 | G5: 452
A6: PROD4 | B6: Women's Yoga Pants | C6: Clothing | D6: Bottoms | E6: Gonzales-Davis | F6: 306.46 | G6: 487
A7: PROD5 | B7: Men's Leather Belt | C7: Clothing | D7: Accessories | E7: Baldwin, Garza and Gonzalez | F7: 261 | G7: 59
A8: PROD6 | B8: Herbal Face Moisturizer | C8: Beauty | D8: Skincare | E8: Davidson PLC | F8: 312.8 | G8: 350
A9: PROD7 | B9: LED Table Lamp | C9: Home | D9: Lighting | E9: Harrell LLC | F9: 218.86 | G9: 170
A10: PROD8 | B10: Wireless Bluetooth Earbuds | C10: Electronics | D10: Audio | E10: Perez-Johnston | F10: 439.07 | G10: 142
A11: PROD9 | B11: Adjustable Dumbbell Set | C11: Sports | D11: Fitness | E11: Hill PLC | F11: 495.72 | G11: 323
A12: PROD10 | B12: Ceramic Kitchen Bowl Set | C12: Home | D12: Kitchen | E12: Hamilton Group | F12: 298.86 | G12: 308
A13: PROD11 | B13: HD Smart TV Stick | C13: Electronics | D13: Accessories | E13: Gibson, Hobbs and Weaver | F13: 449.4 | G13: 270.80233
... A101: PROD99 | B101: Stainless Steel Cookware Set | C101: Home | D101: Kitchen | E101: Campbell Ltd | F101: 201.41 | G101: 146

Sheet Store_Dim
A1: Store_ID | B1: Store_Name | C1: Region | D1: City | E1: Store_Type
A2: STORE0 | B2: Rivera-Warner | C2: East | D2: Washingtonfurt | E2: Flagship
A3: STORE1 | B3: Martinez, Adkins and Johnson | C3: North | D3: Danielmouth | E3: Flagship
A4: STORE2 | B4: Black-Horn | C4: South | D4: North Nancyview | E4: Outlet
A5: STORE3 | B5: Johnson-Wright | C5: North | D5: Hoodberg | E5: Outlet
A6: STORE4 | B6: Alexander Group | C6: South | D6: Port Sharon | E6: Online
A7: STORE5 | B7: Gray Ltd | C7: North | D7: New Michaelchester | E7: Outlet
A8: STORE6 | B8: Benson-Elliott | C8: East | D8: Port Josephberg | E8: Online
A9: STORE7 | B9: Martinez-Mullins | C9: South | D9: Williamsfurt | E9: Online
A10: STORE8 | B10: Bean, Jones and Park | C10: West | D10: Thompsonborough | E10: Online
A11: STORE9 | B11: Moore, Padilla and Butler | C11: South | D11: East Johnstad | E11: Flagship
A12: STORE10 | B12: Hill, Wagner and Ballard | C12: East | D12: East Davidville | E12: Online
... A21: STORE19 | B21: Mann-Austin | C21: East | D21: Vasquezborough | E21: Online

Sheet worksheet.
A1: Sales_ID | B1: Order_Date | C1: Customer_ID | D1: Product_ID | E1: Store_ID | F1: Quantity | G1: Unit_Price | H1: Discount | I1: Payment_Type | J1: Total_Amount | K1: Name | L1: Age | M1: Gender | N1: City | O1: State | P1: Country | Q1: Loyalty_Level | S1: Quantity | T1: Unit_Price | U1: Discount | V1: Total_Amount | X1: Quantity | Y1: Unit_Price | Z1: Discount | AA1: Total_Amount
A2: SALE0 | B2: 45480 | C2: CUST1409 | D2: PROD97 | E2: STORE3 | F2: 1 | G2: 218.04 | H2: 0.09 | I2: Credit Card | J2: 198.4164 | K2: Sarah Smith | L2: 48 | M2: {=VLOOKUP(C2:C2001,Table3[#All],4,1)} -> Female | N2: =VLOOKUP(C:C,Customer_Dim!B:I,5,1) -> Kathleenport | O2: =VLOOKUP(C:C,Customer_Dim!B:I,6,1) -> Wyoming | P2: =VLOOKUP(C:C,Customer_Dim!B:I,7,1) -> USA | Q2: =VLOOKUP(C:C,Customer_Dim!B:I,8,1) -> Gold | S2: 1 | T2: 218.04 | U2: 0.09 | V2: 198.4164 | X2: 1 | Y2: 218.04 | Z2: 0.09 | AA2: 198.4164
A3: SALE1 | B3: 45285 | C3: CUST1467 | D3: PROD74 | E3: STORE17 | F3: 3 | G3: 104.47 | H3: 0.27 | I3: PayPal | J3: 228.7893 | K3: Michael Foley | L3: 45 | M3: Male | N3: =VLOOKUP(C:C,Customer_Dim!B:I,5,1) -> Oneillfurt | O3: =VLOOKUP(C:C,Customer_Dim!B:I,6,1) -> Vermont | P3: =VLOOKUP(C:C,Customer_Dim!B:I,7,1) -> USA | Q3: =VLOOKUP(C:C,Customer_Dim!B:I,8,1) -> Gold | S3: 3 | T3: 104.47 | U3: 0.27 | V3: 228.7893 | X3: 3 | Y3: 104.47 | Z3: 0.27 | AA3: 228.7893
A4: SALE2 | B4: 45446 | C4: CUST1056 | D4: PROD49 | E4: STORE8 | F4: 4 | G4: 914.05 | H4: 0.25 | I4: Credit Card | J4: 2742.15 | K4: Christopher Sutton | L4: 43 | M4: Female | N4: =VLOOKUP(C:C,Customer_Dim!B:I,5,1) -> Deborahberg | O4: =VLOOKUP(C:C,Customer_Dim!B:I,6,1) -> Pennsylvania | P4: =VLOOKUP(C:C,Customer_Dim!B:I,7,1) -> USA | Q4: =VLOOKUP(C:C,Customer_Dim!B:I,8,1) -> Gold | S4: 4 | T4: 914.05 | U4: 0.25 | V4: 2742.15 | X4: 4 | Y4: 914.05 | Z4: 0.25 | AA4: 2742.15
A5: SALE3 | B5: 45259 | C5: CUST1346 | D5: PROD76 | E5: STORE8 | F5: 1 | G5: 921.51 | H5: 0.16 | I5: COD | J5: 774.0684 | K5: John Jordan | L5: 39 | M5: Female | N5: =VLOOKUP(C:C,Customer_Dim!B:I,5,1) -> Port Crystalberg | O5: =VLOOKUP(C:C,Customer_Dim!B:I,6,1) -> Tennessee | P5: =VLOOKUP(C:C,Customer_Dim!B:I,7,1) -> USA | Q5: =VLOOKUP(C:C,Customer_Dim!B:I,8,1) -> Platinum | S5: 1 | T5: 921.51 | U5: 0.16 | V5: 774.0684 | X5: 1 | Y5: 921.51 | Z5: 0.16 | AA5: 774.0684
A6: SALE4 | B6: 45297 | C6: CUST1493 | D6: PROD59 | E6: STORE5 | F6: 3 | G6: 745.3 | H6: 0.18 | I6: Credit Card | J6: 1833.438 | K6: Amanda Powell | L6: 21 | M6: Male | N6: =VLOOKUP(C:C,Customer_Dim!B:I,5,1) -> South William | O6: =VLOOKUP(C:C,Customer_Dim!B:I,6,1) -> Alabama | P6: =VLOOKUP(C:C,Customer_Dim!B:I,7,1) -> USA | Q6: =VLOOKUP(C:C,Customer_Dim!B:I,8,1) -> Silver | S6: 3 | T6: 745.3 | U6: 0.18 | V6: 1833.438 | X6: 3 | Y6: 745.3 | Z6: 0.18 | AA6: 1833.438
A7: SALE5 | B7: 45499 | C7: CUST1116 | D7: PROD15 | E7: STORE7 | F7: 3 | G7: 147.01 | H7: 0.19 | I7: COD | J7: 357.2343 | K7: Anthony Phillips | L7: 21 | M7: Female | N7: =VLOOKUP(C:C,Customer_Dim!B:I,5,1) -> North Davidport | O7: =VLOOKUP(C:C,Customer_Dim!B:I,6,1) -> Rhode Island | P7: =VLOOKUP(C:C,Customer_Dim!B:I,7,1) -> USA | Q7: =VLOOKUP(C:C,Customer_Dim!B:I,8,1) -> Platinum | S7: 3 | T7: 147.01 | U7: 0.19 | V7: 357.2343 | X7: 3 | Y7: 147.01 | Z7: 0.19 | AA7: 357.2343
A8: SALE6 | B8: 45850 | C8: CUST1016 | D8: PROD56 | E8: STORE4 | F8: 2 | G8: 785.31 | H8: 0.15 | I8: PayPal | J8: 1335.027 | K8: John Scott | L8: 60 | M8: Female | N8: =VLOOKUP(C:C,Customer_Dim!B:I,5,1) -> South Christopher | O8: =VLOOKUP(C:C,Customer_Dim!B:I,6,1) -> Pennsylvania | P8: =VLOOKUP(C:C,Customer_Dim!B:I,7,1) -> USA | Q8: =VLOOKUP(C:C,Customer_Dim!B:I,8,1) -> Bronze | S8: 2 | T8: 785.31 | U8: 0.15 | V8: 1335.027 | X8: 2 | Y8: 785.31 | Z8: 0.15 | AA8: 1335.027
A9: SALE7 | B9: 45248 | C9: CUST1152 | D9: PROD70 | E9: STORE8 | F9: 4 | G9: 342.39 | H9: 0.23 | I9: PayPal | J9: 1054.5612 | K9: Patrick Roberts | L9: 31 | M9: Male | N9: =VLOOKUP(C:C,Customer_Dim!B:I,5,1) -> Jaredville | O9: =VLOOKUP(C:C,Customer_Dim!B:I,6,1) -> Missouri | P9: =VLOOKUP(C:C,Customer_Dim!B:I,7,1) -> USA | Q9: =VLOOKUP(C:C,Customer_Dim!B:I,8,1) -> Platinum | S9: 4 | T9: 342.39 | U9: 0.23 | V9: 1054.5612 | X9: 4 | Y9: 342.39 | Z9: 0.23 | AA9: 1054.5612
A10: SALE8 | B10: 45781 | C10: CUST1187 | D10: PROD99 | E10: STORE5 | F10: 2.4796175 | G10: 448.25 | H10: 0.07 | I10: PayPal | J10: 1250.6175 | K10: Dr. Suzanne Bullock | L10: 42 | M10: Male | N10: =VLOOKUP(C:C,Customer_Dim!B:I,5,1) -> Lake Blaketon | O10: =VLOOKUP(C:C,Customer_Dim!B:I,6,1) -> Alabama | P10: =VLOOKUP(C:C,Customer_Dim!B:I,7,1) -> USA | Q10: =VLOOKUP(C:C,Customer_Dim!B:I,8,1) -> Platinum | T10: 448.25 | U10: 0.07 | V10: 1250.6175 | X10: 2.4796175 | Y10: 448.25 | Z10: 0.07 | AA10: 1250.6175
A11: SALE9 | B11: 45869 | C11: CUST1464 | D11: PROD33 | E11: STORE0 | F11: 2 | G11: 873.17 | H11: 0.23 | I11: PayPal | J11: 1344.6818 | K11: David Pierce | L11: 28 | M11: Female | N11: =VLOOKUP(C:C,Customer_Dim!B:I,5,1) -> Grayland | O11: =VLOOKUP(C:C,Customer_Dim!B:I,6,1) -> Washington | P11: =VLOOKUP(C:C,Customer_Dim!B:I,7,1) -> USA | Q11: =VLOOKUP(C:C,Customer_Dim!B:I,8,1) -> Platinum | S11: 2 | T11: 873.17 | U11: 0.23 | V11: 1344.6818 | X11: 2 | Y11: 873.17 | Z11: 0.23 | AA11: 1344.6818
A12: SALE10 | B12: 45335 | C12: CUST1065 | D12: PROD24 | E12: STORE14 | F12: 1 | G12: 278.63 | H12: 0.07 | I12: Credit Card | J12: 259.1259 | K12: Michael Thomas | L12: 27 | M12: Female | N12: =VLOOKUP(C:C,Customer_Dim!B:I,5,1) -> Woodmouth | O12: =VLOOKUP(C:C,Customer_Dim!B:I,6,1) -> Nevada | P12: =VLOOKUP(C:C,Customer_Dim!B:I,7,1) -> USA | Q12: =VLOOKUP(C:C,Customer_Dim!B:I,8,1) -> Silver | S12: 1 | T12: 278.63 | U12: 0.07 | V12: 259.1259 | X12: 1 | Y12: 278.63 | Z12: 0.07 | AA12: 259.1259
A13: SALE11 | B13: 45801 | C13: CUST1320 | D13: PROD39 | E13: STORE1 | F13: 4 | G13: 286.92 | H13: 0.17 | I13: Credit Card | J13: 952.5744 | K13: Jessica Gonzalez | L13: 21 | M13: Female | N13: =VLOOKUP(C:C,Customer_Dim!B:I,5,1) -> South Darrenland | O13: =VLOOKUP(C:C,Customer_Dim!B:I,6,1) -> Iowa | P13: =VLOOKUP(C:C,Customer_Dim!B:I,7,1) -> USA | Q13: =VLOOKUP(C:C,Customer_Dim!B:I,8,1) -> Bronze | S13: 4 | T13: 286.92 | U13: 0.17 | V13: 952.5744 | X13: 4 | Y13: 286.92 | Z13: 0.17 | AA13: 952.5744
A14: SALE12 | B14: 45528 | C14: CUST1237 | D14: PROD88 | E14: STORE4 | F14: 4 | G14: 644.58 | H14: 0.01 | I14: Credit Card | J14: 2552.5368 | K14: Wesley Short | L14: 40 | M14: Male | N14: =VLOOKUP(C:C,Customer_Dim!B:I,5,1) -> Susanstad | O14: =VLOOKUP(C:C,Customer_Dim!B:I,6,1) -> Montana | P14: =VLOOKUP(C:C,Customer_Dim!B:I,7,1) -> USA | Q14: =VLOOKUP(C:C,Customer_Dim!B:I,8,1) -> Gold | S14: 4 | T14: 644.58 | U14: 0.01 | V14: 2552.5368 | X14: 4 | Y14: 644.58 | Z14: 0.01 | AA14: 2552.5368
A15: SALE13 | B15: 45875 | C15: CUST1443 | D15: PROD34 | E15: STORE16 | F15: 2 | G15: 316.9 | H15: 0.3 | I15: PayPal | J15: 443.66 | K15: Adam Castro | L15: 19 | M15: Male | N15: =VLOOKUP(C:C,Customer_Dim!B:I,5,1) -> New Donnabury | O15: =VLOOKUP(C:C,Customer_Dim!B:I,6,1) -> Texas | P15: =VLOOKUP(C:C,Customer_Dim!B:I,7,1) -> USA | Q15: =VLOOKUP(C:C,Customer_Dim!B:I,8,1) -> Silver | S15: 2 | T15: 316.9 | U15: 0.3 | V15: 443.66 | X15: 2 | Y15: 316.9 | Z15: 0.3 | AA15: 443.66
A16: SALE14 | B16: 45829 | C16: CUST1348 | D16: PROD24 | E16: STORE15 | F16: 4 | G16: 403.47 | H16: 0.29 | I16: PayPal | J16: 1145.8548 | K16: Sherry Cabrera | L16: 31 | M16: Male | N16: =VLOOKUP(C:C,Customer_Dim!B:I,5,1) -> Shannonview | O16: =VLOOKUP(C:C,Customer_Dim!B:I,6,1) -> Pennsylvania | P16: =VLOOKUP(C:C,Customer_Dim!B:I,7,1) -> USA | Q16: =VLOOKUP(C:C,Customer_Dim!B:I,8,1) -> Silver | S16: 4 | T16: 403.47 | U16: 0.29 | V16: 1145.8548 | X16: 4 | Y16: 403.47 | Z16: 0.29 | AA16: 1145.8548
A17: SALE15 | B17: 45636 | C17: CUST1435 | D17: PROD36 | E17: STORE9 | F17: 2.4785462 | G17: 871.34 | H17: 0.04 | I17: COD | J17: 2509.4592 | K17: Lindsay Beasley | L17: 61 | M17: Male | N17: =VLOOKUP(C:C,Customer_Dim!B:I,5,1) -> Wesleyhaven | O17: =VLOOKUP(C:C,Customer_Dim!B:I,6,1) -> Idaho | P17: =VLOOKUP(C:C,Customer_Dim!B:I,7,1) -> USA | Q17: =VLOOKUP(C:C,Customer_Dim!B:I,8,1) -> Silver | T17: 871.34 | U17: 0.04 | V17: 2509.4592 | X17: 2.4785462 | Y17: 871.34 | Z17: 0.04 | AA17: 2509.4592
A18: SALE16 | B18: 45913 | C18: CUST1276 | D18: PROD65 | E18: STORE19 | F18: 2 | G18: 451.98 | H18: 0.25 | I18: Credit Card | J18: 677.97 | K18: Arthur Warren | L18: 22 | M18: Female | N18: =VLOOKUP(C:C,Customer_Dim!B:I,5,1) -> Ericshire | O18: =VLOOKUP(C:C,Customer_Dim!B:I,6,1) -> Nevada | P18: =VLOOKUP(C:C,Customer_Dim!B:I,7,1) -> USA | Q18: =VLOOKUP(C:C,Customer_Dim!B:I,8,1) -> Gold | S18: 2 | T18: 451.98 | U18: 0.25 | V18: 677.97 | X18: 2 | Y18: 451.98 | Z18: 0.25 | AA18: 677.97
A19: SALE17 | B19: 45637 | C19: CUST1079 | D19: PROD27 | E19: STORE4 | F19: 2 | G19: 502.69 | H19: 0.23 | I19: Credit Card | J19: 774.1426 | K19: Molly Gardner | L19: 61 | M19: Female | N19: =VLOOKUP(C:C,Customer_Dim!B:I,5,1) -> Nicoleborough | O19: =VLOOKUP(C:C,Customer_Dim!B:I,6,1) -> Arkansas | P19: =VLOOKUP(C:C,Customer_Dim!B:I,7,1) -> USA | Q19: =VLOOKUP(C:C,Customer_Dim!B:I,8,1) -> Platinum | S19: 2 | T19: 502.69 | U19: 0.23 | V19: 774.1426 | X19: 2 | Y19: 502.69 | Z19: 0.23 | AA19: 774.1426
A20: SALE18 | B20: 45517 | C20: CUST1094 | D20: PROD39 | E20: STORE4 | F20: 2 | G20: 559.23 | H20: 0.25 | I20: COD | J20: 838.845 | K20: David Patterson | L20: 62 | M20: Female | N20: =VLOOKUP(C:C,Customer_Dim!B:I,5,1) -> New Amyport | O20: =VLOOKUP(C:C,Customer_Dim!B:I,6,1) -> Nevada | P20: =VLOOKUP(C:C,Customer_Dim!B:I,7,1) -> USA | Q20: =VLOOKUP(C:C,Customer_Dim!B:I,8,1) -> Gold | S20: 2 | T20: 559.23 | U20: 0.25 | V20: 838.845 | X20: 2 | Y20: 559.23 | Z20: 0.25 | AA20: 838.845
A21: SALE19 | B21: 45369 | C21: CUST1239 | D21: PROD60 | E21: STORE13 | F21: 4 | G21: 513.95973 | H21: 0.04 | I21: COD | J21: 1782.4512 | K21: Maria Hill | L21: 59 | M21: Female | N21: =VLOOKUP(C:C,Customer_Dim!B:I,5,1) -> Zamoraborough | O21: =VLOOKUP(C:C,Customer_Dim!B:I,6,1) -> Nevada | P21: =VLOOKUP(C:C,Customer_Dim!B:I,7,1) -> USA | Q21: =VLOOKUP(C:C,Customer_Dim!B:I,8,1) -> Platinum | S21: 4 | U21: 0.04 | V21: 1782.4512 | X21: 4 | Y21: 513.95973 | Z21: 0.04 | AA21: 1782.4512
A22: SALE20 | B22: 45843 | C22: CUST1144 | D22: PROD72 | E22: STORE17 | F22: 3 | G22: 986.04 | H22: 0.27 | I22: COD | J22: 2159.4276 | K22: Justin Cross | L22: 46 | M22: Male | N22: =VLOOKUP(C:C,Customer_Dim!B:I,5,1) -> North Anthonychester | O22: =VLOOKUP(C:C,Customer_Dim!B:I,6,1) -> Nevada | P22: =VLOOKUP(C:C,Customer_Dim!B:I,7,1) -> USA | Q22: =VLOOKUP(C:C,Customer_Dim!B:I,8,1) -> Bronze | S22: 3 | T22: 986.04 | U22: 0.27 | V22: 2159.4276 | X22: 3 | Y22: 986.04 | Z22: 0.27 | AA22: 2159.4276
A23: SALE21 | B23: 45447 | C23: CUST1396 | D23: PROD43 | E23: STORE18 | F23: 1 | G23: 589.56 | H23: 0.22 | I23: Credit Card | J23: 459.8568 | K23: Alexander Byrd | L23: 62 | M23: Female | N23: =VLOOKUP(C:C,Customer_Dim!B:I,5,1) -> Parkerview | O23: =VLOOKUP(C:C,Customer_Dim!B:I,6,1) -> New York | P23: =VLOOKUP(C:C,Customer_Dim!B:I,7,1) -> USA | Q23: =VLOOKUP(C:C,Customer_Dim!B:I,8,1) -> Silver | S23: 1 | T23: 589.56 | U23: 0.22 | V23: 459.8568 | X23: 1 | Y23: 589.56 | Z23: 0.22 | AA23: 459.8568
A24: SALE22 | B24: 45394 | C24: CUST1476 | D24: PROD69 | E24: STORE10 | F24: 3 | G24: 979.42 | H24: 0.03 | I24: PayPal | J24: 2850.1122 | K24: Elizabeth Foster | L24: 41 | M24: Female | N24: =VLOOKUP(C:C,Customer_Dim!B:I,5,1) -> Anthonymouth | O24: =VLOOKUP(C:C,Customer_Dim!B:I,6,1) -> Oklahoma | P24: =VLOOKUP(C:C,Customer_Dim!B:I,7,1) -> USA | Q24: =VLOOKUP(C:C,Customer_Dim!B:I,8,1) -> Gold | S24: 3 | T24: 979.42 | U24: 0.03 | V24: 2850.1122 | X24: 3 | Y24: 979.42 | Z24: 0.03 | AA24: 2850.1122
A25: SALE23 | B25: 45466 | C25: CUST1368 | D25: PROD12 | E25: STORE8 | F25: 1 | G25: 719.28 | H25: 0.08 | I25: Credit Card | J25: 661.7376 | K25: Miranda King | L25: 20 | M25: Female | N25: =VLOOKUP(C:C,Customer_Dim!B:I,5,1) -> West Mathew | O25: =VLOOKUP(C:C,Customer_Dim!B:I,6,1) -> New York | P25: =VLOOKUP(C:C,Customer_Dim!B:I,7,1) -> USA | Q25: =VLOOKUP(C:C,Customer_Dim!B:I,8,1) -> Platinum | S25: 1 | T25: 719.28 | U25: 0.08 | V25: 661.7376 | X25: 1 | Y25: 719.28 | Z25: 0.08 | AA25: 661.7376
A26: SALE24 | B26: 45908 | C26: CUST1186 | D26: PROD67 | E26: STORE6 | F26: 3 | G26: 77.6 | H26: 0.07 | I26: Credit Card | J26: 216.504 | K26: Jennifer Pruitt | L26: 60 | M26: Female | N26: =VLOOKUP(C:C,Customer_Dim!B:I,5,1) -> East Justin | O26: =VLOOKUP(C:C,Customer_Dim!B:I,6,1) -> Missouri | P26: =VLOOKUP(C:C,Customer_Dim!B:I,7,1) -> USA | Q26: =VLOOKUP(C:C,Customer_Dim!B:I,8,1) -> Silver | S26: 3 | T26: 77.6 | U26: 0.07 | V26: 216.504 | X26: 3 | Y26: 77.6 | Z26: 0.07 | AA26: 216.504
A27: SALE25 | B27: 45552 | C27: CUST1381 | D27: PROD5 | E27: STORE3 | F27: 4 | G27: 852.71 | H27: 0.14 | I27: PayPal | J27: 2933.3224 | K27: Erika Padilla | L27: 20 | M27: Female | N27: =VLOOKUP(C:C,Customer_Dim!B:I,5,1) -> Andrewsland | O27: =VLOOKUP(C:C,Customer_Dim!B:I,6,1) -> Alabama | P27: =VLOOKUP(C:C,Customer_Dim!B:I,7,1) -> USA | Q27: =VLOOKUP(C:C,Customer_Dim!B:I,8,1) -> Silver | S27: 4 | T27: 852.71 | U27: 0.14 | V27: 2933.3224 | X27: 4 | Y27: 852.71 | Z27: 0.14 | AA27: 2933.3224
A28: SALE26 | B28: 45294 | C28: CUST1213 | D28: PROD98 | E28: STORE8 | F28: 4 | G28: 156.16 | H28: 0.14786802 | I28: Credit Card | J28: 599.6544 | K28: Stuart Johnson | L28: 61 | M28: Male | N28: =VLOOKUP(C:C,Customer_Dim!B:I,5,1) -> West Markport | O28: =VLOOKUP(C:C,Customer_Dim!B:I,6,1) -> North Dakota | P28: =VLOOKUP(C:C,Customer_Dim!B:I,7,1) -> USA | Q28: =VLOOKUP(C:C,Customer_Dim!B:I,8,1) -> Platinum | S28: 4 | T28: 156.16 | V28: 599.6544 | X28: 4 | Y28: 156.16 | Z28: 0.14786802 | AA28: 599.6544
A29: SALE27 | B29: 45710 | C29: CUST1200 | D29: PROD77 | E29: STORE8 | F29: 3 | G29: 815.49 | H29: 0.17 | I29: Credit Card | J29: 2030.5701 | K29: Anna Perez | L29: 25 | M29: Female | N29: =VLOOKUP(C:C,Customer_Dim!B:I,5,1) -> South Jerry | O29: =VLOOKUP(C:C,Customer_Dim!B:I,6,1) -> Maine | P29: =VLOOKUP(C:C,Customer_Dim!B:I,7,1) -> USA | Q29: =VLOOKUP(C:C,Customer_Dim!B:I,8,1) -> Platinum | S29: 3 | T29: 815.49 | U29: 0.17 | V29: 2030.5701 | X29: 3 | Y29: 815.49 | Z29: 0.17 | AA29: 2030.5701
A30: SALE28 | B30: 45923 | C30: CUST1148 | D30: PROD13 | E30: STORE2 | F30: 2 | G30: 74.21 | H30: 0.11 | I30: PayPal | J30: 132.0938 | K30: Theresa Campbell | L30: 33 | M30: Male | N30: =VLOOKUP(C:C,Customer_Dim!B:I,5,1) -> New Brian | O30: =VLOOKUP(C:C,Customer_Dim!B:I,6,1) -> Wisconsin | P30: =VLOOKUP(C:C,Customer_Dim!B:I,7,1) -> USA | Q30: =VLOOKUP(C:C,Customer_Dim!B:I,8,1) -> Bronze | S30: 2 | T30: 74.21 | U30: 0.11 | V30: 132.0938 | X30: 2 | Y30: 74.21 | Z30: 0.11 | AA30: 132.0938
A31: SALE29 | B31: 45302 | C31: CUST1348 | D31: PROD99 | E31: STORE3 | F31: 2.4776423 | G31: 451.67 | H31: 0.15 | I31: Credit Card | J31: 1535.678 | K31: Sherry Cabrera | L31: 31 | M31: Male | N31: =VLOOKUP(C:C,Customer_Dim!B:I,5,1) -> Shannonview | O31: =VLOOKUP(C:C,Customer_Dim!B:I,6,1) -> Pennsylvania | P31: =VLOOKUP(C:C,Customer_Dim!B:I,7,1) -> USA | Q31: =VLOOKUP(C:C,Customer_Dim!B:I,8,1) -> Silver | T31: 451.67 | U31: 0.15 | V31: 1535.678 | X31: 2.4776423 | Y31: 451.67 | Z31: 0.15 | AA31: 1535.678
A32: SALE30 | B32: 45217 | C32: CUST1028 | D32: PROD5 | E32: STORE19 | F32: 1 | G32: 429.38 | H32: 0.13 | I32: PayPal | J32: 373.5606 | K32: Joshua Ryan | L32: 54 | M32: Female | N32: =VLOOKUP(C:C,Customer_Dim!B:I,5,1) -> New David | O32: =VLOOKUP(C:C,Customer_Dim!B:I,6,1) -> New Jersey | P32: =VLOOKUP(C:C,Customer_Dim!B:I,7,1) -> USA | Q32: =VLOOKUP(C:C,Customer_Dim!B:I,8,1) -> Platinum | S32: 1 | T32: 429.38 | U32: 0.13 | V32: 373.5606 | X32: 1 | Y32: 429.38 | Z32: 0.13 | AA32: 373.5606
A33: SALE31 | B33: 45593 | C33: CUST1412 | D33: PROD53 | E33: STORE12 | F33: 2 | G33: 148.96 | H33: 0.03 | I33: COD | J33: 288.9824 | K33: Shane Brown | L33: 59 | M33: Female | N33: =VLOOKUP(C:C,Customer_Dim!B:I,5,1) -> East Andrea | O33: =VLOOKUP(C:C,Customer_Dim!B:I,6,1) -> Michigan | P33: =VLOOKUP(C:C,Customer_Dim!B:I,7,1) -> USA | Q33: =VLOOKUP(C:C,Customer_Dim!B:I,8,1) -> Gold | S33: 2 | T33: 148.96 | U33: 0.03 | V33: 288.9824 | X33: 2 | Y33: 148.96 | Z33: 0.03 | AA33: 288.9824
A34: SALE32 | B34: 45597 | C34: CUST1398 | D34: PROD75 | E34: STORE8 | F34: 4 | G34: 313.83 | H34: 0.08 | I34: Credit Card | J34: 1154.8944 | K34: Jennifer Johnson | L34: 27 | M34: Male | N34: =VLOOKUP(C:C,Customer_Dim!B:I,5,1) -> Cheyenneborough | O34: =VLOOKUP(C:C,Customer_Dim!B:I,6,1) -> New Hampshire | P34: =VLOOKUP(C:C,Customer_Dim!B:I,7,1) -> USA | Q34: =VLOOKUP(C:C,Customer_Dim!B:I,8,1) -> Bronze | S34: 4 | T34: 313.83 | U34: 0.08 | V34: 1154.8944 | X34: 4 | Y34: 313.83 | Z34: 0.08 | AA34: 1154.8944
A35: SALE33 | B35: 45620 | C35: CUST1453 | D35: PROD12 | E35: STORE6 | F35: 2 | G35: 717.31 | H35: 0.15 | I35: Credit Card | J35: 1219.427 | K35: April Phillips | L35: 60 | M35: Male | N35: =VLOOKUP(C:C,Customer_Dim!B:I,5,1) -> Lake Carolyn | O35: =VLOOKUP(C:C,Customer_Dim!B:I,6,1) -> Hawaii | P35: =VLOOKUP(C:C,Customer_Dim!B:I,7,1) -> USA | Q35: =VLOOKUP(C:C,Customer_Dim!B:I,8,1) -> Platinum | S35: 2 | T35: 717.31 | U35: 0.15 | V35: 1219.427 | X35: 2 | Y35: 717.31 | Z35: 0.15 | AA35: 1219.427
A36: SALE34 | B36: 45215 | C36: CUST1344 | D36: PROD79 | E36: STORE1 | F36: 2.4781059 | G36: 873.22 | H36: 0.18 | I36: Credit Card | J36: 2148.1212 | K36: Evelyn Brown | L36: 33 | M36: Male | N36: =VLOOKUP(C:C,Customer_Dim!B:I,5,1) -> West Victoriaborough | O36: =VLOOKUP(C:C,Customer_Dim!B:I,6,1) -> New Mexico | P36: =VLOOKUP(C:C,Customer_Dim!B:I,7,1) -> USA | Q36: =VLOOKUP(C:C,Customer_Dim!B:I,8,1) -> Gold | T36: 873.22 | U36: 0.18 | V36: 2148.1212 | X36: 2.4781059 | Y36: 873.22 | Z36: 0.18 | AA36: 2148.1212
A37: SALE35 | B37: 45878 | C37: CUST1218 | D37: PROD16 | E37: STORE3 | F37: 4 | G37: 109.36 | H37: 0.19 | I37: COD | J37: 354.3264 | K37: Julia Jackson | L37: 47 | M37: Female | N37: =VLOOKUP(C:C,Customer_Dim!B:I,5,1) -> Edwardland | O37: =VLOOKUP(C:C,Customer_Dim!B:I,6,1) -> California | P37: =VLOOKUP(C:C,Customer_Dim!B:I,7,1) -> USA | Q37: =VLOOKUP(C:C,Customer_Dim!B:I,8,1) -> Platinum | S37: 4 | T37: 109.36 | U37: 0.19 | V37: 354.3264 | X37: 4 | Y37: 109.36 | Z37: 0.19 | AA37: 354.3264
A38: SALE36 | B38: 45635 | C38: CUST1086 | D38: PROD5 | E38: STORE7 | F38: 3 | G38: 559.52 | H38: 0.16 | I38: PayPal | J38: 1409.9904 | K38: Tammy Miller Md | L38: 58 | M38: Female | N38: =VLOOKUP(C:C,Customer_Dim!B:I,5,1) -> Austinfurt | O38: =VLOOKUP(C:C,Customer_Dim!B:I,6,1) -> Mississippi | P38: =VLOOKUP(C:C,Customer_Dim!B:I,7,1) -> USA | Q38: =VLOOKUP(C:C,Customer_Dim!B:I,8,1) -> Gold | S38: 3 | T38: 559.52 | U38: 0.16 | V38: 1409.9904 | X38: 3 | Y38: 559.52 | Z38: 0.16 | AA38: 1409.9904
A39: SALE37 | B39: 45329 | C39: CUST1492 | D39: PROD10 | E39: STORE17 | F39: 3 | G39: 121.76 | H39: 0.27 | I39: PayPal | J39: 266.6544 | K39: Darrell Miller | L39: 28 | M39: Male | N39: =VLOOKUP(C:C,Customer_Dim!B:I,5,1) -> Port Carol | O39: =VLOOKUP(C:C,Customer_Dim!B:I,6,1) -> Florida | P39: =VLOOKUP(C:C,Customer_Dim!B:I,7,1) -> USA | Q39: =VLOOKUP(C:C,Customer_Dim!B:I,8,1) -> Platinum | S39: 3 | T39: 121.76 | U39: 0.27 | V39: 266.6544 | X39: 3 | Y39: 121.76 | Z39: 0.27 | AA39: 266.6544
A40: SALE38 | B40: 45378 | C40: CUST1189 | D40: PROD33 | E40: STORE13 | F40: 4 | G40: 735.32 | H40: 0.06 | I40: COD | J40: 2764.8032 | K40: Daniel Austin | L40: 21 | M40: Male | N40: =VLOOKUP(C:C,Customer_Dim!B:I,5,1) -> Lake Howardberg | O40: =VLOOKUP(C:C,Customer_Dim!B:I,6,1) -> Kentucky | P40: =VLOOKUP(C:C,Customer_Dim!B:I,7,1) -> USA | Q40: =VLOOKUP(C:C,Customer_Dim!B:I,8,1) -> Gold | S40: 4 | T40: 735.32 | U40: 0.06 | V40: 2764.8032 | X40: 4 | Y40: 735.32 | Z40: 0.06 | AA40: 2764.8032
A41: SALE39 | B41: 45264 | C41: CUST1431 | D41: PROD94 | E41: STORE3 | F41: 2 | G41: 600.73 | H41: 0.08 | I41: Credit Card | J41: 1105.3432 | K41: John Smith | L41: 37 | M41: Male | N41: =VLOOKUP(C:C,Customer_Dim!B:I,5,1) -> South Andrewport | O41: =VLOOKUP(C:C,Customer_Dim!B:I,6,1) -> California | P41: =VLOOKUP(C:C,Customer_Dim!B:I,7,1) -> USA | Q41: =VLOOKUP(C:C,Customer_Dim!B:I,8,1) -> Platinum | S41: 2 | T41: 600.73 | U41: 0.08 | V41: 1105.3432 | X41: 2 | Y41: 600.73 | Z41: 0.08 | AA41: 1105.3432
A42: SALE40 | B42: 45486 | C42: CUST1072 | D42: PROD26 | E42: STORE19 | F42: 2 | G42: 873.86 | H42: 0.07 | I42: COD | J42: 1625.3796 | K42: Tonya Burch | L42: 56 | M42: Female | N42: =VLOOKUP(C:C,Customer_Dim!B:I,5,1) -> Olsonhaven | O42: =VLOOKUP(C:C,Customer_Dim!B:I,6,1) -> Iowa | P42: =VLOOKUP(C:C,Customer_Dim!B:I,7,1) -> USA | Q42: =VLOOKUP(C:C,Customer_Dim!B:I,8,1) -> Gold | S42: 2 | T42: 873.86 | U42: 0.07 | V42: 1625.3796 | X42: 2 | Y42: 873.86 | Z42: 0.07 | AA42: 1625.3796
A43: SALE41 | B43: 45241 | C43: CUST1302 | D43: PROD23 | E43: STORE8 | F43: 3 | G43: 342.47 | H43: 0.08 | I43: PayPal | J43: 945.2172 | K43: Edward Cole | L43: 23 | M43: Female | N43: =VLOOKUP(C:C,Customer_Dim!B:I,5,1) -> Lake Charlotte | O43: =VLOOKUP(C:C,Customer_Dim!B:I,6,1) -> Arizona | P43: =VLOOKUP(C:C,Customer_Dim!B:I,7,1) -> USA | Q43: =VLOOKUP(C:C,Customer_Dim!B:I,8,1) -> Gold | S43: 3 | T43: 342.47 | U43: 0.08 | V43: 945.2172 | X43: 3 | Y43: 342.47 | Z43: 0.08 | AA43: 945.2172
A44: SALE42 | B44: 45649 | C44: CUST1335 | D44: PROD29 | E44: STORE9 | F44: 2 | G44: 915.15 | H44: 0.16 | I44: PayPal | J44: 1537.452 | K44: Jennifer Woods | L44: 58 | M44: Female | N44: =VLOOKUP(C:C,Customer_Dim!B:I,5,1) -> West Brendamouth | O44: =VLOOKUP(C:C,Customer_Dim!B:I,6,1) -> North Carolina | P44: =VLOOKUP(C:C,Customer_Dim!B:I,7,1) -> USA | Q44: =VLOOKUP(C:C,Customer_Dim!B:I,8,1) -> Platinum | S44: 2 | T44: 915.15 | U44: 0.16 | V44: 1537.452 | X44: 2 | Y44: 915.15 | Z44: 0.16 | AA44: 1537.452
A45: SALE43 | B45: 45677 | C45: CUST1084 | D45: PROD33 | E45: STORE17 | F45: 2.4764826 | G45: 863.11 | H45: 0.28 | I45: PayPal | J45: 1864.3176 | K45: Christy Hoffman | L45: 36 | M45: Male | N45: =VLOOKUP(C:C,Customer_Dim!B:I,5,1) -> Garyberg | O45: =VLOOKUP(C:C,Customer_Dim!B:I,6,1) -> Indiana | P45: =VLOOKUP(C:C,Customer_Dim!B:I,7,1) -> USA | Q45: =VLOOKUP(C:C,Customer_Dim!B:I,8,1) -> Platinum | T45: 863.11 | U45: 0.28 | V45: 1864.3176 | X45: 2.4764826 | Y45: 863.11 | Z45: 0.28 | AA45: 1864.3176
A46: SALE44 | B46: 45538 | C46: CUST1203 | D46: PROD43 | E46: STORE12 | F46: 2 | G46: 209.32 | H46: 0.23 | I46: COD | J46: 322.3528 | K46: Sarah Brady | L46: 52 | M46: Male | N46: =VLOOKUP(C:C,Customer_Dim!B:I,5,1) -> Johnsonland | O46: =VLOOKUP(C:C,Customer_Dim!B:I,6,1) -> Iowa | P46: =VLOOKUP(C:C,Customer_Dim!B:I,7,1) -> USA | Q46: =VLOOKUP(C:C,Customer_Dim!B:I,8,1) -> Platinum | S46: 2 | T46: 209.32 | U46: 0.23 | V46: 322.3528 | X46: 2 | Y46: 209.32 | Z46: 0.23 | AA46: 322.3528
A47: SALE45 | B47: 45606 | C47: CUST1470 | D47: PROD59 | E47: STORE8 | F47: 4 | G47: 288.6 | H47: 0.09 | I47: PayPal | J47: 1050.504 | K47: Manuel Fisher | L47: 42 | M47: Male | N47: =VLOOKUP(C:C,Customer_Dim!B:I,5,1) -> Kanebury | O47: =VLOOKUP(C:C,Customer_Dim!B:I,6,1) -> New Hampshire | P47: =VLOOKUP(C:C,Customer_Dim!B:I,7,1) -> USA | Q47: =VLOOKUP(C:C,Customer_Dim!B:I,8,1) -> Gold | S47: 4 | T47: 288.6 | U47: 0.09 | V47: 1050.504 | X47: 4 | Y47: 288.6 | Z47: 0.09 | AA47: 1050.504
A48: SALE46 | B48: 45570 | C48: CUST1070 | D48: PROD78 | E48: STORE16 | F48: 1 | G48: 418.69 | H48: 0.06 | I48: PayPal | J48: 393.5686 | K48: Eric Singh | L48: 61 | M48: Female | N48: =VLOOKUP(C:C,Customer_Dim!B:I,5,1) -> Port Lisa | O48: =VLOOKUP(C:C,Customer_Dim!B:I,6,1) -> New Mexico | P48: =VLOOKUP(C:C,Customer_Dim!B:I,7,1) -> USA | Q48: =VLOOKUP(C:C,Customer_Dim!B:I,8,1) -> Gold | S48: 1 | T48: 418.69 | U48: 0.06 | V48: 393.5686 | X48: 1 | Y48: 418.69 | Z48: 0.06 | AA48: 393.5686
A49: SALE47 | B49: 45466 | C49: CUST1008 | D49: PROD30 | E49: STORE11 | F49: 1 | G49: 135.78 | H49: 0.14 | I49: PayPal | J49: 116.7708 | K49: Melissa Howard | L49: 64 | M49: Male | N49: =VLOOKUP(C:C,Customer_Dim!B:I,5,1) -> Maynardton | O49: =VLOOKUP(C:C,Customer_Dim!B:I,6,1) -> New Hampshire | P49: =VLOOKUP(C:C,Customer_Dim!B:I,7,1) -> USA | Q49: =VLOOKUP(C:C,Customer_Dim!B:I,8,1) -> Gold | S49: 1 | T49: 135.78 | U49: 0.14 | V49: 116.7708 | X49: 1 | Y49: 135.78 | Z49: 0.14 | AA49: 116.7708
A50: SALE48 | B50: 45218 | C50: CUST1203 | D50: PROD44 | E50: STORE17 | F50: 1 | G50: 517.13 | H50: 0.28 | I50: Credit Card | J50: 372.3336 | K50: Sarah Brady | L50: 52 | M50: Male | N50: =VLOOKUP(C:C,Customer_Dim!B:I,5,1) -> Johnsonland | O50: =VLOOKUP(C:C,Customer_Dim!B:I,6,1) -> Iowa | P50: =VLOOKUP(C:C,Customer_Dim!B:I,7,1) -> USA | Q50: =VLOOKUP(C:C,Customer_Dim!B:I,8,1) -> Platinum | S50: 1 | T50: 517.13 | U50: 0.28 | V50: 372.3336 | X50: 1 | Y50: 517.13 | Z50: 0.28 | AA50: 372.3336
A51: SALE49 | B51: 45607 | C51: CUST1420 | D51: PROD21 | E51: STORE16 | F51: 2 | G51: 384.66 | H51: 0.08 | I51: COD | J51: 707.7744 | K51: Dr. Tamara White Md | L51: 45 | M51: Female | N51: =VLOOKUP(C:C,Customer_Dim!B:I,5,1) -> New Benjamin | O51: =VLOOKUP(C:C,Customer_Dim!B:I,6,1) -> North Carolina | P51: =VLOOKUP(C:C,Customer_Dim!B:I,7,1) -> USA | Q51: =VLOOKUP(C:C,Customer_Dim!B:I,8,1) -> Bronze | S51: 2 | T51: 384.66 | U51: 0.08 | V51: 707.7744 | X51: 2 | Y51: 384.66 | Z51: 0.08 | AA51: 707.7744
A52: SALE50 | B52: 45291 | C52: CUST1070 | D52: PROD52 | E52: STORE9 | F52: 3 | G52: 83.7 | H52: 0.24 | I52: PayPal | J52: 190.836 | K52: Eric Singh | L52: 61 | M52: Female | N52: =VLOOKUP(C:C,Customer_Dim!B:I,5,1) -> Port Lisa | O52: =VLOOKUP(C:C,Customer_Dim!B:I,6,1) -> New Mexico | P52: =VLOOKUP(C:C,Customer_Dim!B:I,7,1) -> USA | Q52: =VLOOKUP(C:C,Customer_Dim!B:I,8,1) -> Gold | S52: 3 | T52: 83.7 | U52: 0.24 | V52: 190.836 | X52: 3 | Y52: 83.7 | Z52: 0.24 | AA52: 190.836
A53: SALE51 | B53: 45689 | C53: CUST1142 | D53: PROD69 | E53: STORE7 | F53: 3 | G53: 76.57 | H53: 0.26 | I53: Credit Card | J53: 169.9854 | K53: Maria Ramirez | L53: 46 | M53: Male | N53: =VLOOKUP(C:C,Customer_Dim!B:I,5,1) -> West Brandon | O53: =VLOOKUP(C:C,Customer_Dim!B:I,6,1) -> Montana | P53: =VLOOKUP(C:C,Customer_Dim!B:I,7,1) -> USA | Q53: =VLOOKUP(C:C,Customer_Dim!B:I,8,1) -> Bronze | S53: 3 | T53: 76.57 | U53: 0.26 | V53: 169.9854 | X53: 3 | Y53: 76.57 | Z53: 0.26 | AA53: 169.9854
A54: SALE52 | B54: 45894 | C54: CUST1148 | D54: PROD89 | E54: STORE6 | F54: 3 | G54: 514.48704 | H54: 0.1478509 | I54: Credit Card | J54: 486.0633 | K54: Theresa Campbell | L54: 33 | M54: Male | N54: =VLOOKUP(C:C,Customer_Dim!B:I,5,1) -> New Brian | O54: =VLOOKUP(C:C,Customer_Dim!B:I,6,1) -> Wisconsin | P54: =VLOOKUP(C:C,Customer_Dim!B:I,7,1) -> USA | Q54: =VLOOKUP(C:C,Customer_Dim!B:I,8,1) -> Bronze | S54: 3 | V54: 486.0633 | X54: 3 | Y54: 514.48704 | Z54: 0.1478509 | AA54: 486.0633
A55: SALE53 | B55: 45677 | C55: CUST1324 | D55: PROD20 | E55: STORE8 | F55: 1 | G55: 900.35 | H55: 0.13 | I55: COD | J55: 783.3045 | K55: Alex Mann Ii | L55: 60 | M55: Male | N55: =VLOOKUP(C:C,Customer_Dim!B:I,5,1) -> South Zacharychester | O55: =VLOOKUP(C:C,Customer_Dim!B:I,6,1) -> Oklahoma | P55: =VLOOKUP(C:C,Customer_Dim!B:I,7,1) -> USA | Q55: =VLOOKUP(C:C,Customer_Dim!B:I,8,1) -> Bronze | S55: 1 | T55: 900.35 | U55: 0.13 | V55: 783.3045 | X55: 1 | Y55: 900.35 | Z55: 0.13 | AA55: 783.3045
A56: SALE54 | B56: 45706 | C56: CUST1095 | D56: PROD40 | E56: STORE10 | F56: 4 | G56: 428.09 | H56: 0.07 | I56: Credit Card | J56: 1592.4948 | K56: Amy Fowler | L56: 30 | M56: Female | N56: =VLOOKUP(C:C,Customer_Dim!B:I,5,1) -> West Bobbyshire | O56: =VLOOKUP(C:C,Customer_Dim!B:I,6,1) -> New York | P56: =VLOOKUP(C:C,Customer_Dim!B:I,7,1) -> USA | Q56: =VLOOKUP(C:C,Customer_Dim!B:I,8,1) -> Platinum | S56: 4 | T56: 428.09 | U56: 0.07 | V56: 1592.4948 | X56: 4 | Y56: 428.09 | Z56: 0.07 | AA56: 1592.4948
A57: SALE55 | B57: 45589 | C57: CUST1416 | D57: PROD49 | E57: STORE11 | F57: 2 | G57: 559.71 | H57: 0.3 | I57: COD | J57: 783.594 | K57: Jennifer Myers | L57: 64 | M57: Female | N57: =VLOOKUP(C:C,Customer_Dim!B:I,5,1) -> Marthaborough | O57: =VLOOKUP(C:C,Customer_Dim!B:I,6,1) -> Wisconsin | P57: =VLOOKUP(C:C,Customer_Dim!B:I,7,1) -> USA | Q57: =VLOOKUP(C:C,Customer_Dim!B:I,8,1) -> Platinum | S57: 2 | T57: 559.71 | U57: 0.3 | V57: 783.594 | X57: 2 | Y57: 559.71 | Z57: 0.3 | AA57: 783.594
A58: SALE56 | B58: 45282 | C58: CUST1080 | D58: PROD34 | E58: STORE6 | F58: 2 | G58: 833.7 | H58: 0.06 | I58: PayPal | J58: 1567.356 | K58: Jennifer Garcia | L58: 34 | M58: Female | N58: =VLOOKUP(C:C,Customer_Dim!B:I,5,1) -> New Sean | O58: =VLOOKUP(C:C,Customer_Dim!B:I,6,1) -> New Mexico | P58: =VLOOKUP(C:C,Customer_Dim!B:I,7,1) -> USA | Q58: =VLOOKUP(C:C,Customer_Dim!B:I,8,1) -> Bronze | S58: 2 | T58: 833.7 | U58: 0.06 | V58: 1567.356 | X58: 2 | Y58: 833.7 | Z58: 0.06 | AA58: 1567.356
A59: SALE57 | B59: 45462 | C59: CUST1467 | D59: PROD47 | E59: STORE14 | F59: 2 | G59: 680.16 | H59: 0.28 | I59: Credit Card | J59: 979.4304 | K59: Michael Foley | L59: 45 | M59: Male | N59: =VLOOKUP(C:C,Customer_Dim!B:I,5,1) -> Oneillfurt | O59: =VLOOKUP(C:C,Customer_Dim!B:I,6,1) -> Vermont | P59: =VLOOKUP(C:C,Customer_Dim!B:I,7,1) -> USA | Q59: =VLOOKUP(C:C,Customer_Dim!B:I,8,1) -> Gold | S59: 2 | T59: 680.16 | U59: 0.28 | V59: 979.4304 | X59: 2 | Y59: 680.16 | Z59: 0.28 | AA59: 979.4304
A60: SALE58 | B60: 45633 | C60: CUST1404 | D60: PROD15 | E60: STORE7 | F60: 4 | G60: 733.42 | H60: 0.14779897 | I60: PayPal | J60: 2552.3016 | K60: David Ross | L60: 18 | M60: Female | N60: =VLOOKUP(C:C,Customer_Dim!B:I,5,1) -> South Angela | O60: =VLOOKUP(C:C,Customer_Dim!B:I,6,1) -> Arkansas | P60: =VLOOKUP(C:C,Customer_Dim!B:I,7,1) -> USA | Q60: =VLOOKUP(C:C,Customer_Dim!B:I,8,1) -> Silver | S60: 4 | T60: 733.42 | V60: 2552.3016 | X60: 4 | Y60: 733.42 | Z60: 0.14779897 | AA60: 2552.3016
A61: SALE59 | B61: 45257 | C61: CUST1367 | D61: PROD89 | E61: STORE11 | F61: 1 | G61: 996.33 | H61: 0.23 | I61: PayPal | J61: 767.1741 | K61: Melinda Johnson | L61: 34 | M61: Female | N61: =VLOOKUP(C:C,Customer_Dim!B:I,5,1) -> Kaufmanfurt | O61: =VLOOKUP(C:C,Customer_Dim!B:I,6,1) -> Ohio | P61: =VLOOKUP(C:C,Customer_Dim!B:I,7,1) -> USA | Q61: =VLOOKUP(C:C,Customer_Dim!B:I,8,1) -> Bronze | S61: 1 | T61: 996.33 | U61: 0.23 | V61: 767.1741 | X61: 1 | Y61: 996.33 | Z61: 0.23 | AA61: 767.1741
A62: SALE60 | B62: 45854 | C62: CUST1408 | D62: PROD31 | E62: STORE10 | F62: 1 | G62: 198.83 | H62: 0.09 | I62: COD | J62: 180.9353 | K62: Isabel Foster | L62: 55 | M62: Male | N62: =VLOOKUP(C:C,Customer_Dim!B:I,5,1) -> Port Joshuaville | O62: =VLOOKUP(C:C,Customer_Dim!B:I,6,1) -> New Jersey | P62: =VLOOKUP(C:C,Customer_Dim!B:I,7,1) -> USA | Q62: =VLOOKUP(C:C,Customer_Dim!B:I,8,1) -> Gold | S62: 1 | T62: 198.83 | U62: 0.09 | V62: 180.9353 | X62: 1 | Y62: 198.83 | Z62: 0.09 | AA62: 180.9353
A63: SALE61 | B63: 45716 | C63: CUST1239 | D63: PROD19 | E63: STORE7 | F63: 1 | G63: 374.92 | H63: 0.18 | I63: PayPal | J63: 307.4344 | K63: Maria Hill | L63: 59 | M63: Female | N63: =VLOOKUP(C:C,Customer_Dim!B:I,5,1) -> Zamoraborough | O63: =VLOOKUP(C:C,Customer_Dim!B:I,6,1) -> Nevada | P63: =VLOOKUP(C:C,Customer_Dim!B:I,7,1) -> USA | Q63: =VLOOKUP(C:C,Customer_Dim!B:I,8,1) -> Platinum | S63: 1 | T63: 374.92 | U63: 0.18 | V63: 307.4344 | X63: 1 | Y63: 374.92 | Z63: 0.18 | AA63: 307.4344
A64: SALE62 | B64: 45515 | C64: CUST1464 | D64: PROD93 | E64: STORE16 | F64: 1 | G64: 468.94 | H64: 0.12 | I64: Credit Card | J64: 412.6672 | K64: David Pierce | L64: 28 | M64: Female | N64: =VLOOKUP(C:C,Customer_Dim!B:I,5,1) -> Grayland | O64: =VLOOKUP(C:C,Customer_Dim!B:I,6,1) -> Washington | P64: =VLOOKUP(C:C,Customer_Dim!B:I,7,1) -> USA | Q64: =VLOOKUP(C:C,Customer_Dim!B:I,8,1) -> Platinum | S64: 1 | T64: 468.94 | U64: 0.12 | V64: 412.6672 | X64: 1 | Y64: 468.94 | Z64: 0.12 | AA64: 412.6672
A65: SALE63 | B65: 45927 | C65: CUST1126 | D65: PROD89 | E65: STORE12 | F65: 2 | G65: 121.37 | H65: 0.05 | I65: Credit Card | J65: 230.603 | K65: James Wolfe | L65: 39 | M65: Male | N65: =VLOOKUP(C:C,Customer_Dim!B:I,5,1) -> Benjaminton | O65: =VLOOKUP(C:C,Customer_Dim!B:I,6,1) -> Arizona | P65: =VLOOKUP(C:C,Customer_Dim!B:I,7,1) -> USA | Q65: =VLOOKUP(C:C,Customer_Dim!B:I,8,1) -> Gold | S65: 2 | T65: 121.37 | U65: 0.05 | V65: 230.603 | X65: 2 | Y65: 121.37 | Z65: 0.05 | AA65: 230.603
A66: SALE64 | B66: 45914 | C66: CUST1255 | D66: PROD53 | E66: STORE10 | F66: 3 | G66: 480.06 | H66: 0.01 | I66: Credit Card | J66: 1088.6371 | K66: Damon Perez | L66: 57 | M66: Male | N66: =VLOOKUP(C:C,Customer_Dim!B:I,5,1) -> Jasonton | O66: =VLOOKUP(C:C,Customer_Dim!B:I,6,1) -> Ohio | P66: =VLOOKUP(C:C,Customer_Dim!B:I,7,1) -> USA | Q66: =VLOOKUP(C:C,Customer_Dim!B:I,8,1) -> Gold | S66: 3 | T66: 480.06 | U66: 0.01 | X66: 3 | Y66: 480.06 | Z66: 0.01 | AA66: 1088.6371
A67: SALE65 | B67: 45290 | C67: CUST1162 | D67: PROD99 | E67: STORE17 | F67: 2 | G67: 856.57 | H67: 0.24 | I67: Credit Card | J67: 1301.9864 | K67: Mariah Brown | L67: 21 | M67: Male | N67: =VLOOKUP(C:C,Customer_Dim!B:I,5,1) -> Palmerbury | O67: =VLOOKUP(C:C,Customer_Dim!B:I,6,1) -> Tennessee | P67: =VLOOKUP(C:C,Customer_Dim!B:I,7,1) -> USA | Q67: =VLOOKUP(C:C,Customer_Dim!B:I,8,1) -> Silver | S67: 2 | T67: 856.57 | U67: 0.24 | V67: 1301.9864 | X67: 2 | Y67: 856.57 | Z67: 0.24 | AA67: 1301.9864
A68: SALE66 | B68: 45213 | C68: CUST1269 | D68: PROD77 | E68: STORE2 | F68: 4 | G68: 814.25 | H68: 0.18 | I68: Credit Card | J68: 2670.74 | K68: Tyrone Olson | L68: 31 | M68: Female | N68: =VLOOKUP(C:C,Customer_Dim!B:I,5,1) -> Emilytown | O68: =VLOOKUP(C:C,Customer_Dim!B:I,6,1) -> California | P68: =VLOOKUP(C:C,Customer_Dim!B:I,7,1) -> USA | Q68: =VLOOKUP(C:C,Customer_Dim!B:I,8,1) -> Silver | S68: 4 | T68: 814.25 | U68: 0.18 | V68: 2670.74 | X68: 4 | Y68: 814.25 | Z68: 0.18 | AA68: 2670.74
A69: SALE67 | B69: 45255 | C69: CUST1483 | D69: PROD12 | E69: STORE2 | F69: 1 | G69: 989.17 | H69: 0.2 | I69: PayPal | J69: 791.336 | K69: Sarah Smith | L69: 32 | M69: Male | N69: =VLOOKUP(C:C,Customer_Dim!B:I,5,1) -> East Rodney | O69: =VLOOKUP(C:C,Customer_Dim!B:I,6,1) -> Nevada | P69: =VLOOKUP(C:C,Customer_Dim!B:I,7,1) -> USA | Q69: =VLOOKUP(C:C,Customer_Dim!B:I,8,1) -> Gold | S69: 1 | T69: 989.17 | U69: 0.2 | V69: 791.336 | X69: 1 | Y69: 989.17 | Z69: 0.2 | AA69: 791.336
A70: SALE68 | B70: 45270 | C70: CUST1372 | D70: PROD72 | E70: STORE10 | F70: 4 | G70: 62.48 | H70: 0.18 | I70: Credit Card | J70: 204.9344 | K70: Jacqueline Anthony | L70: 37 | M70: Female | N70: =VLOOKUP(C:C,Customer_Dim!B:I,5,1) -> Vincentside | O70: =VLOOKUP(C:C,Customer_Dim!B:I,6,1) -> Ohio | P70: =VLOOKUP(C:C,Customer_Dim!B:I,7,1) -> USA | Q70: =VLOOKUP(C:C,Customer_Dim!B:I,8,1) -> Bronze | S70: 4 | T70: 62.48 | U70: 0.18 | V70: 204.9344 | X70: 4 | Y70: 62.48 | Z70: 0.18 | AA70: 204.9344
A71: SALE69 | B71: 45897 | C71: CUST1423 | D71: PROD13 | E71: STORE16 | F71: 4 | G71: 561.24 | H71: 0.24 | I71: Credit Card | J71: 1706.1696 | K71: Rebecca Baker | L71: 53 | M71: Male | N71: =VLOOKUP(C:C,Customer_Dim!B:I,5,1) -> New Katherine | O71: =VLOOKUP(C:C,Customer_Dim!B:I,6,1) -> Kansas | P71: =VLOOKUP(C:C,Customer_Dim!B:I,7,1) -> USA | Q71: =VLOOKUP(C:C,Customer_Dim!B:I,8,1) -> Silver | S71: 4 | T71: 561.24 | U71: 0.24 | V71: 1706.1696 | X71: 4 | Y71: 561.24 | Z71: 0.24 | AA71: 1706.1696
A72: SALE70 | B72: 45849 | C72: CUST1058 | D72: PROD60 | E72: STORE5 | F72: 3 | G72: 92.24 | H72: 0.28 | I72: COD | J72: 1087.9978 | K72: Cheryl Copeland | L72: 53 | M72: Male | N72: =VLOOKUP(C:C,Customer_Dim!B:I,5,1) -> Snowmouth | O72: =VLOOKUP(C:C,Customer_Dim!B:I,6,1) -> Maryland | P72: =VLOOKUP(C:C,Customer_Dim!B:I,7,1) -> USA | Q72: =VLOOKUP(C:C,Customer_Dim!B:I,8,1) -> Platinum | S72: 3 | T72: 92.24 | U72: 0.28 | X72: 3 | Y72: 92.24 | Z72: 0.28 | AA72: 1087.9978
A73: SALE71 | B73: 45889 | C73: CUST1168 | D73: PROD72 | E73: STORE1 | F73: 2 | G73: 668.3 | H73: 0.07 | I73: Credit Card | J73: 1243.038 | K73: Daniel Contreras | L73: 64 | M73: Male | N73: =VLOOKUP(C:C,Customer_Dim!B:I,5,1) -> Robertview | O73: =VLOOKUP(C:C,Customer_Dim!B:I,6,1) -> Florida | P73: =VLOOKUP(C:C,Customer_Dim!B:I,7,1) -> USA | Q73: =VLOOKUP(C:C,Customer_Dim!B:I,8,1) -> Platinum | S73: 2 | T73: 668.3 | U73: 0.07 | V73: 1243.038 | X73: 2 | Y73: 668.3 | Z73: 0.07 | AA73: 1243.038
A74: SALE72 | B74: 45533 | C74: CUST1409 | D74: PROD38 | E74: STORE5 | F74: 1 | G74: 553.82 | H74: 0.09 | I74: Credit Card | J74: 503.9762 | K74: Sarah Smith | L74: 48 | M74: Female | N74: =VLOOKUP(C:C,Customer_Dim!B:I,5,1) -> Kathleenport | O74: =VLOOKUP(C:C,Customer_Dim!B:I,6,1) -> Wyoming | P74: =VLOOKUP(C:C,Customer_Dim!B:I,7,1) -> USA | Q74: =VLOOKUP(C:C,Customer_Dim!B:I,8,1) -> Gold | S74: 1 | T74: 553.82 | U74: 0.09 | V74: 503.9762 | X74: 1 | Y74: 553.82 | Z74: 0.09 | AA74: 503.9762
A75: SALE73 | B75: 45626 | C75: CUST1037 | D75: PROD45 | E75: STORE11 | F75: 2 | G75: 556.43 | H75: 0.13 | I75: Credit Card | J75: 968.1882 | K75: Christopher Carter | L75: 35 | M75: Female | N75: =VLOOKUP(C:C,Customer_Dim!B:I,5,1) -> Brendastad | O75: =VLOOKUP(C:C,Customer_Dim!B:I,6,1) -> South Dakota | P75: =VLOOKUP(C:C,Customer_Dim!B:I,7,1) -> USA | Q75: =VLOOKUP(C:C,Customer_Dim!B:I,8,1) -> Platinum | S75: 2 | T75: 556.43 | U75: 0.13 | V75: 968.1882 | X75: 2 | Y75: 556.43 | Z75: 0.13 | AA75: 968.1882
A76: SALE74 | B76: 45942 | C76: CUST1273 | D76: PROD20 | E76: STORE8 | F76: 1 | G76: 184.98 | H76: 0.1 | I76: COD | J76: 166.482 | K76: Samantha Robinson | L76: 38 | M76: Male | N76: =VLOOKUP(C:C,Customer_Dim!B:I,5,1) -> North Roy | O76: =VLOOKUP(C:C,Customer_Dim!B:I,6,1) -> Mississippi | P76: =VLOOKUP(C:C,Customer_Dim!B:I,7,1) -> USA | Q76: =VLOOKUP(C:C,Customer_Dim!B:I,8,1) -> Bronze | S76: 1 | T76: 184.98 | U76: 0.1 | V76: 166.482 | X76: 1 | Y76: 184.98 | Z76: 0.1 | AA76: 166.482
A77: SALE75 | B77: 45500 | C77: CUST1035 | D77: PROD97 | E77: STORE12 | F77: 4 | G77: 700.18 | H77: 0.23 | I77: Credit Card | J77: 2156.5544 | K77: Rachel Myers | L77: 20 | M77: Female | N77: =VLOOKUP(C:C,Customer_Dim!B:I,5,1) -> Robertberg | O77: =VLOOKUP(C:C,Customer_Dim!B:I,6,1) -> North Dakota | P77: =VLOOKUP(C:C,Customer_Dim!B:I,7,1) -> USA | Q77: =VLOOKUP(C:C,Customer_Dim!B:I,8,1) -> Silver | S77: 4 | T77: 700.18 | U77: 0.23 | V77: 2156.5544 | X77: 4 | Y77: 700.18 | Z77: 0.23 | AA77: 2156.5544
A78: SALE76 | B78: 45285 | C78: CUST1019 | D78: PROD76 | E78: STORE10 | F78: 2 | G78: 686.31 | H78: 0.25 | I78: Credit Card | J78: 1029.465 | K78: Michael Torres | L78: 59 | M78: Male | N78: =VLOOKUP(C:C,Customer_Dim!B:I,5,1) -> Gonzalezfort | O78: =VLOOKUP(C:C,Customer_Dim!B:I,6,1) -> New Jersey | P78: =VLOOKUP(C:C,Customer_Dim!B:I,7,1) -> USA | Q78: =VLOOKUP(C:C,Customer_Dim!B:I,8,1) -> Platinum | S78: 2 | T78: 686.31 | U78: 0.25 | V78: 1029.465 | X78: 2 | Y78: 686.31 | Z78: 0.25 | AA78: 1029.465
A79: SALE77 | B79: 45800 | C79: CUST1007 | D79: PROD67 | E79: STORE15 | F79: 1 | G79: 687.82 | H79: 0.27 | I79: COD | J79: 502.1086 | K79: Daniel Boyd | L79: 53 | M79: Female | N79: =VLOOKUP(C:C,Customer_Dim!B:I,5,1) -> West Pamelafurt | O79: =VLOOKUP(C:C,Customer_Dim!B:I,6,1) -> West Virginia | P79: =VLOOKUP(C:C,Customer_Dim!B:I,7,1) -> USA | Q79: =VLOOKUP(C:C,Customer_Dim!B:I,8,1) -> Bronze | S79: 1 | T79: 687.82 | U79: 0.27 | V79: 502.1086 | X79: 1 | Y79: 687.82 | Z79: 0.27 | AA79: 502.1086
A80: SALE78 | B80: 45609 | C80: CUST1221 | D80: PROD83 | E80: STORE8 | F80: 2 | G80: 900.55 | H80: 0.16 | I80: Credit Card | J80: 1512.924 | K80: Lisa Young | L80: 35 | M80: Male | N80: =VLOOKUP(C:C,Customer_Dim!B:I,5,1) -> Maybury | O80: =VLOOKUP(C:C,Customer_Dim!B:I,6,1) -> Georgia | P80: =VLOOKUP(C:C,Customer_Dim!B:I,7,1) -> USA | Q80: =VLOOKUP(C:C,Customer_Dim!B:I,8,1) -> Platinum | S80: 2 | T80: 900.55 | U80: 0.16 | V80: 1512.924 | X80: 2 | Y80: 900.55 | Z80: 0.16 | AA80: 1512.924
A81: SALE79 | B81: 45268 | C81: CUST1115 | D81: PROD21 | E81: STORE2 | F81: 1 | G81: 341.17 | H81: 0.15 | I81: Credit Card | J81: 289.9945 | K81: Tyler Conrad | L81: 18 | M81: Female | N81: =VLOOKUP(C:C,Customer_Dim!B:I,5,1) -> North Curtischester | O81: =VLOOKUP(C:C,Customer_Dim!B:I,6,1) -> North Dakota | P81: =VLOOKUP(C:C,Customer_Dim!B:I,7,1) -> USA | Q81: =VLOOKUP(C:C,Customer_Dim!B:I,8,1) -> Platinum | S81: 1 | T81: 341.17 | U81: 0.15 | V81: 289.9945 | X81: 1 | Y81: 341.17 | Z81: 0.15 | AA81: 289.9945
A82: SALE80 | B82: 45885 | C82: CUST1176 | D82: PROD52 | E82: STORE8 | F82: 1 | G82: 442.27 | H82: 0.06 | I82: COD | J82: 415.7338 | K82: John Bradford | L82: 55 | M82: Male | N82: =VLOOKUP(C:C,Customer_Dim!B:I,5,1) -> Anabury | O82: =VLOOKUP(C:C,Customer_Dim!B:I,6,1) -> Vermont | P82: =VLOOKUP(C:C,Customer_Dim!B:I,7,1) -> USA | Q82: =VLOOKUP(C:C,Customer_Dim!B:I,8,1) -> Silver | S82: 1 | T82: 442.27 | U82: 0.06 | V82: 415.7338 | X82: 1 | Y82: 442.27 | Z82: 0.06 | AA82: 415.7338
A83: SALE81 | B83: 45616 | C83: CUST1253 | D83: PROD71 | E83: STORE9 | F83: 1 | G83: 363.73 | H83: 0.25 | I83: PayPal | J83: 272.7975 | K83: Dr. Ashley Yates Md | L83: 34 | M83: Male | N83: =VLOOKUP(C:C,Customer_Dim!B:I,5,1) -> New Maria | O83: =VLOOKUP(C:C,Customer_Dim!B:I,6,1) -> Wisconsin | P83: =VLOOKUP(C:C,Customer_Dim!B:I,7,1) -> USA | Q83: =VLOOKUP(C:C,Customer_Dim!B:I,8,1) -> Bronze | S83: 1 | T83: 363.73 | U83: 0.25 | V83: 272.7975 | X83: 1 | Y83: 363.73 | Z83: 0.25 | AA83: 272.7975
A84: SALE82 | B84: 45518 | C84: CUST1378 | D84: PROD91 | E84: STORE17 | F84: 2 | G84: 601.33 | H84: 0.16 | I84: PayPal | J84: 1010.2344 | K84: Frank Stewart | L84: 34 | M84: Female | N84: =VLOOKUP(C:C,Customer_Dim!B:I,5,1) -> Fischerborough | O84: =VLOOKUP(C:C,Customer_Dim!B:I,6,1) -> Delaware | P84: =VLOOKUP(C:C,Customer_Dim!B:I,7,1) -> USA | Q84: =VLOOKUP(C:C,Customer_Dim!B:I,8,1) -> Bronze | S84: 2 | T84: 601.33 | U84: 0.16 | V84: 1010.2344 | X84: 2 | Y84: 601.33 | Z84: 0.16 | AA84: 1010.2344
A85: SALE83 | B85: 45427 | C85: CUST1403 | D85: PROD17 | E85: STORE18 | F85: 4 | G85: 34.39 | H85: 0.03 | I85: PayPal | J85: 133.4332 | K85: Justin Ingram | L85: 22 | M85: Female | N85: =VLOOKUP(C:C,Customer_Dim!B:I,5,1) -> Lake Lisaland | O85: =VLOOKUP(C:C,Customer_Dim!B:I,6,1) -> Louisiana | P85: =VLOOKUP(C:C,Customer_Dim!B:I,7,1) -> USA | Q85: =VLOOKUP(C:C,Customer_Dim!B:I,8,1) -> Bronze | S85: 4 | T85: 34.39 | U85: 0.03 | V85: 133.4332 | X85: 4 | Y85: 34.39 | Z85: 0.03 | AA85: 133.4332
A86: SALE84 | B86: 45268 | C86: CUST1423 | D86: PROD46 | E86: STORE17 | F86: 1 | G86: 773.57 | H86: 0.05 | I86: COD | J86: 1090.0558 | K86: Rebecca Baker | L86: 53 | M86: Male | N86: =VLOOKUP(C:C,Customer_Dim!B:I,5,1) -> New Katherine | O86: =VLOOKUP(C:C,Customer_Dim!B:I,6,1) -> Kansas | P86: =VLOOKUP(C:C,Customer_Dim!B:I,7,1) -> USA | Q86: =VLOOKUP(C:C,Customer_Dim!B:I,8,1) -> Silver | S86: 1 | T86: 773.57 | U86: 0.05 | X86: 1 | Y86: 773.57 | Z86: 0.05 | AA86: 1090.0558
A87: SALE85 | B87: 45282 | C87: CUST1054 | D87: PROD88 | E87: STORE7 | F87: 4 | G87: 127.1 | H87: 0.24 | I87: COD | J87: 386.384 | K87: Katherine Dorsey | L87: 56 | M87: Female | N87: =VLOOKUP(C:C,Customer_Dim!B:I,5,1) -> Christopherland | O87: =VLOOKUP(C:C,Customer_Dim!B:I,6,1) -> Oklahoma | P87: =VLOOKUP(C:C,Customer_Dim!B:I,7,1) -> USA | Q87: =VLOOKUP(C:C,Customer_Dim!B:I,8,1) -> Platinum | S87: 4 | T87: 127.1 | U87: 0.24 | V87: 386.384 | X87: 4 | Y87: 127.1 | Z87: 0.24 | AA87: 386.384
A88: SALE86 | B88: 45545 | C88: CUST1303 | D88: PROD20 | E88: STORE3 | F88: 3 | G88: 899.58 | H88: 0.28 | I88: PayPal | J88: 1943.0928 | K88: John Sloan | L88: 41 | M88: Male | N88: =VLOOKUP(C:C,Customer_Dim!B:I,5,1) -> East Johntown | O88: =VLOOKUP(C:C,Customer_Dim!B:I,6,1) -> Delaware | P88: =VLOOKUP(C:C,Customer_Dim!B:I,7,1) -> USA | Q88: =VLOOKUP(C:C,Customer_Dim!B:I,8,1) -> Platinum | S88: 3 | T88: 899.58 | U88: 0.28 | V88: 1943.0928 | X88: 3 | Y88: 899.58 | Z88: 0.28 | AA88: 1943.0928
A89: SALE87 | B89: 45755 | C89: CUST1327 | D89: PROD1 | E89: STORE10 | F89: 3 | G89: 964.39 | H89: 0.04 | I89: Credit Card | J89: 2777.4432 | K89: Reginald Willis | L89: 46 | M89: Male | N89: =VLOOKUP(C:C,Customer_Dim!B:I,5,1) -> Kellybury | O89: =VLOOKUP(C:C,Customer_Dim!B:I,6,1) -> New York | P89: =VLOOKUP(C:C,Customer_Dim!B:I,7,1) -> USA | Q89: =VLOOKUP(C:C,Customer_Dim!B:I,8,1) -> Bronze | S89: 3 | T89: 964.39 | U89: 0.04 | V89: 2777.4432 | X89: 3 | Y89: 964.39 | Z89: 0.04 | AA89: 2777.4432
A90: SALE88 | B90: 45588 | C90: CUST1183 | D90: PROD38 | E90: STORE0 | F90: 2 | G90: 217.83 | H90: 0.14 | I90: PayPal | J90: 374.6676 | K90: Mario Jacobs | L90: 46 | M90: Female | N90: =VLOOKUP(C:C,Customer_Dim!B:I,5,1) -> Port James | O90: =VLOOKUP(C:C,Customer_Dim!B:I,6,1) -> New York | P90: =VLOOKUP(C:C,Customer_Dim!B:I,7,1) -> USA | Q90: =VLOOKUP(C:C,Customer_Dim!B:I,8,1) -> Platinum | S90: 2 | T90: 217.83 | U90: 0.14 | V90: 374.6676 | X90: 2 | Y90: 217.83 | Z90: 0.14 | AA90: 374.6676
A91: SALE89 | B91: 45848 | C91: CUST1143 | D91: PROD17 | E91: STORE1 | F91: 4 | G91: 187.71 | H91: 0.06 | I91: COD | J91: 705.7896 | K91: Carlos Skinner | L91: 62 | M91: Female | N91: =VLOOKUP(C:C,Customer_Dim!B:I,5,1) -> Dwaynemouth | O91: =VLOOKUP(C:C,Customer_Dim!B:I,6,1) -> Alabama | P91: =VLOOKUP(C:C,Customer_Dim!B:I,7,1) -> USA | Q91: =VLOOKUP(C:C,Customer_Dim!B:I,8,1) -> Bronze | S91: 4 | T91: 187.71 | U91: 0.06 | V91: 705.7896 | X91: 4 | Y91: 187.71 | Z91: 0.06 | AA91: 705.7896
A92: SALE90 | B92: 45577 | C92: CUST1010 | D92: PROD33 | E92: STORE18 | F92: 2 | G92: 350.12 | H92: 0.12 | I92: COD | J92: 616.2112 | K92: Dominic Page | L92: 28 | M92: Female | N92: =VLOOKUP(C:C,Customer_Dim!B:I,5,1) -> Port Michaelburgh | O92: =VLOOKUP(C:C,Customer_Dim!B:I,6,1) -> Pennsylvania | P92: =VLOOKUP(C:C,Customer_Dim!B:I,7,1) -> USA | Q92: =VLOOKUP(C:C,Customer_Dim!B:I,8,1) -> Bronze | S92: 2 | T92: 350.12 | U92: 0.12 | V92: 616.2112 | X92: 2 | Y92: 350.12 | Z92: 0.12 | AA92: 616.2112
A93: SALE91 | B93: 45312 | C93: CUST1406 | D93: PROD16 | E93: STORE1 | F93: 4 | G93: 102.19 | H93: 0.17 | I93: PayPal | J93: 339.2708 | K93: David Lozano | L93: 33 | M93: Male | N93: =VLOOKUP(C:C,Customer_Dim!B:I,5,1) -> North Michaelfurt | O93: =VLOOKUP(C:C,Customer_Dim!B:I,6,1) -> Wisconsin | P93: =VLOOKUP(C:C,Customer_Dim!B:I,7,1) -> USA | Q93: =VLOOKUP(C:C,Customer_Dim!B:I,8,1) -> Gold | S93: 4 | T93: 102.19 | U93: 0.17 | V93: 339.2708 | X93: 4 | Y93: 102.19 | Z93: 0.17 | AA93: 339.2708
A94: SALE92 | B94: 45350 | C94: CUST1007 | D94: PROD86 | E94: STORE4 | F94: 1 | G94: 696.53 | H94: 0.17 | I94: Credit Card | J94: 578.1199 | K94: Daniel Boyd | L94: 53 | M94: Female | N94: =VLOOKUP(C:C,Customer_Dim!B:I,5,1) -> West Pamelafurt | O94: =VLOOKUP(C:C,Customer_Dim!B:I,6,1) -> West Virginia | P94: =VLOOKUP(C:C,Customer_Dim!B:I,7,1) -> USA | Q94: =VLOOKUP(C:C,Customer_Dim!B:I,8,1) -> Bronze | S94: 1 | T94: 696.53 | U94: 0.17 | V94: 578.1199 | X94: 1 | Y94: 696.53 | Z94: 0.17 | AA94: 578.1199
A95: SALE93 | B95: 45657 | C95: CUST1065 | D95: PROD19 | E95: STORE4 | F95: 2 | G95: 327.52 | H95: 0.15 | I95: PayPal | J95: 556.784 | K95: Michael Thomas | L95: 27 | M95: Female | N95: =VLOOKUP(C:C,Customer_Dim!B:I,5,1) -> Woodmouth | O95: =VLOOKUP(C:C,Customer_Dim!B:I,6,1) -> Nevada | P95: =VLOOKUP(C:C,Customer_Dim!B:I,7,1) -> USA | Q95: =VLOOKUP(C:C,Customer_Dim!B:I,8,1) -> Silver | S95: 2 | T95: 327.52 | U95: 0.15 | V95: 556.784 | X95: 2 | Y95: 327.52 | Z95: 0.15 | AA95: 556.784
A96: SALE94 | B96: 45530 | C96: CUST1298 | D96: PROD97 | E96: STORE19 | F96: 2 | G96: 569.36 | H96: 0.01 | I96: PayPal | J96: 1090.8604 | K96: Tracy Stephens | L96: 48 | M96: Female | N96: =VLOOKUP(C:C,Customer_Dim!B:I,5,1) -> New Joshuatown | O96: =VLOOKUP(C:C,Customer_Dim!B:I,6,1) -> Maine | P96: =VLOOKUP(C:C,Customer_Dim!B:I,7,1) -> USA | Q96: =VLOOKUP(C:C,Customer_Dim!B:I,8,1) -> Platinum | S96: 2 | T96: 569.36 | U96: 0.01 | X96: 2 | Y96: 569.36 | Z96: 0.01 | AA96: 1090.8604
A97: SALE95 | B97: 45556 | C97: CUST1321 | D97: PROD99 | E97: STORE6 | F97: 2 | G97: 68.29 | H97: 0.14 | I97: COD | J97: 117.4588 | K97: Darren Burton | L97: 54 | M97: Male | N97: =VLOOKUP(C:C,Customer_Dim!B:I,5,1) -> Lake Alice | O97: =VLOOKUP(C:C,Customer_Dim!B:I,6,1) -> Tennessee | P97: =VLOOKUP(C:C,Customer_Dim!B:I,7,1) -> USA | Q97: =VLOOKUP(C:C,Customer_Dim!B:I,8,1) -> Bronze | S97: 2 | T97: 68.29 | U97: 0.14 | V97: 117.4588 | X97: 2 | Y97: 68.29 | Z97: 0.14 | AA97: 117.4588
A98: SALE96 | B98: 45523 | C98: CUST1244 | D98: PROD50 | E98: STORE10 | F98: 1 | G98: 842.9 | H98: 0.06 | I98: COD | J98: 792.326 | K98: Nancy Page | L98: 57 | M98: Female | N98: =VLOOKUP(C:C,Customer_Dim!B:I,5,1) -> West Julia | O98: =VLOOKUP(C:C,Customer_Dim!B:I,6,1) -> Utah | P98: =VLOOKUP(C:C,Customer_Dim!B:I,7,1) -> USA | Q98: =VLOOKUP(C:C,Customer_Dim!B:I,8,1) -> Bronze | S98: 1 | T98: 842.9 | U98: 0.06 | V98: 792.326 | X98: 1 | Y98: 842.9 | Z98: 0.06 | AA98: 792.326
A99: SALE97 | B99: 45587 | C99: CUST1287 | D99: PROD3 | E99: STORE3 | F99: 3 | G99: 751.94 | H99: 0.26 | I99: PayPal | J99: 1669.3068 | K99: Cynthia Roberts | L99: 58 | M99: Male | N99: =VLOOKUP(C:C,Customer_Dim!B:I,5,1) -> Millerfort | O99: =VLOOKUP(C:C,Customer_Dim!B:I,6,1) -> Vermont | P99: =VLOOKUP(C:C,Customer_Dim!B:I,7,1) -> USA | Q99: =VLOOKUP(C:C,Customer_Dim!B:I,8,1) -> Gold | S99: 3 | T99: 751.94 | U99: 0.26 | V99: 1669.3068 | X99: 3 | Y99: 751.94 | Z99: 0.26 | AA99: 1669.3068
A100: SALE98 | B100: 45580 | C100: CUST1131 | D100: PROD56 | E100: STORE7 | F100: 4 | G100: 476.28 | H100: 0.17 | I100: Credit Card | J100: 1581.2496 | K100: Joseph Richards | L100: 57 | M100: Female | N100: =VLOOKUP(C:C,Customer_Dim!B:I,5,1) -> Wigginsville | O100: =VLOOKUP(C:C,Customer_Dim!B:I,6,1) -> Alabama | P100: =VLOOKUP(C:C,Customer_Dim!B:I,7,1) -> USA | Q100: =VLOOKUP(C:C,Customer_Dim!B:I,8,1) -> Bronze | S100: 4 | T100: 476.28 | U100: 0.17 | V100: 1581.2496 | X100: 4 | Y100: 476.28 | Z100: 0.17 | AA100: 1581.2496
...

Sheet Total Sales 
A1: Sales_ID | B1: Order_Date | C1: Customer_ID | D1: Product_ID | E1: Store_ID | F1: Quantity | G1: Unit_Price | H1: Discount | I1: Payment_Type | J1: Total_Amount | K1: Name | L1: Age | M1: Gender | N1: City | O1: State | P1: Country | Q1: Loyalty_Level | R1: Product_Name | S1: Category | T1: Sub_Category | U1: Brand | V1: Store_Name | W1: Region | X1: Store_Type
A2: SALE0 | B2: 45480 | C2: CUST1409 | D2: PROD97 | E2: STORE3 | F2: 1 | G2: 218.04 | H2: 0.09 | I2: Credit Card | J2: 198.4164 | K2: Sarah Smith | L2: 48 | M2: Female | N2: Kathleenport | O2: Wyoming | P2: USA | Q2: Gold | R2: Cricket Bat | S2: Sports | T2: Team Sports | U2: Khan LLC | V2: Johnson-Wright | W2: North | X2: Outlet
A3: SALE1 | B3: 45285 | C3: CUST1467 | D3: PROD74 | E3: STORE17 | F3: 3 | G3: 104.47 | H3: 0.27 | I3: PayPal | J3: 228.7893 | K3: Michael Foley | L3: 45 | M3: Male | N3: Oneillfurt | O3: Vermont | P3: USA | Q3: Gold | R3: Bluetooth Car Audio System | S3: Electronics | T3: Audio | U3: Bruce-Bowen | V3: Martinez, Adkins and Johnson | W3: North | X3: Flagship
A4: SALE2 | B4: 45446 | C4: CUST1056 | D4: PROD49 | E4: STORE8 | F4: 4 | G4: 914.05 | H4: 0.25 | I4: Credit Card | J4: 2742.15 | K4: Christopher Sutton | L4: 43 | M4: Female | N4: Deborahberg | O4: Pennsylvania | P4: USA | Q4: Gold | R4: Men's Roll-On Perfume | S4: Beauty | T4: Fragrance | U4: Sullivan and Sons | V4: Bean, Jones and Park | W4: West | X4: Online
A5: SALE3 | B5: 45259 | C5: CUST1346 | D5: PROD76 | E5: STORE8 | F5: 1 | G5: 921.51 | H5: 0.16 | I5: COD | J5: 774.0684 | K5: John Jordan | L5: 39 | M5: Female | N5: Port Crystalberg | O5: Tennessee | P5: USA | Q5: Platinum | R5: Wireless Mouse | S5: Electronics | T5: Computer | U5: Larson Ltd | V5: Bean, Jones and Park | W5: West | X5: Online
A6: SALE4 | B6: 45297 | C6: CUST1493 | D6: PROD59 | E6: STORE5 | F6: 3 | G6: 745.3 | H6: 0.18 | I6: Credit Card | J6: 1833.438 | K6: Amanda Powell | L6: 21 | M6: Male | N6: South William | O6: Alabama | P6: USA | Q6: Silver | R6: Men's Hair Styling Gel | S6: Beauty | T6: Haircare | U6: Cline-Mccarthy | V6: Gray Ltd | W6: North | X6: Outlet
A7: SALE5 | B7: 45499 | C7: CUST1116 | D7: PROD15 | E7: STORE7 | F7: 3 | G7: 147.01 | H7: 0.19 | I7: COD | J7: 357.2343 | K7: Anthony Phillips | L7: 21 | M7: Female | N7: North Davidport | O7: Rhode Island | P7: USA | Q7: Platinum | R7: 4K Home Projector | S7: Electronics | T7: Appliances | U7: Thomas LLC | V7: Martinez-Mullins | W7: South | X7: Online
A8: SALE6 | B8: 45850 | C8: CUST1016 | D8: PROD56 | E8: STORE4 | F8: 2 | G8: 785.31 | H8: 0.15 | I8: PayPal | J8: 1335.027 | K8: John Scott | L8: 60 | M8: Female | N8: South Christopher | O8: Pennsylvania | P8: USA | Q8: Bronze | R8: Premium Blanket Throw | S8: Home | T8: Decor | U8: Hernandez, Kennedy and Porter | V8: Alexander Group | W8: South | X8: Online
A9: SALE7 | B9: 45248 | C9: CUST1152 | D9: PROD70 | E9: STORE8 | F9: 4 | G9: 342.39 | H9: 0.23 | I9: PayPal | J9: 1054.5612 | K9: Patrick Roberts | L9: 31 | M9: Male | N9: Jaredville | O9: Missouri | P9: USA | Q9: Platinum | R9: Kitchen Storage Rack | S9: Home | T9: Storage | U9: Duran Group | V9: Bean, Jones and Park | W9: West | X9: Online
A10: SALE8 | B10: 45781 | C10: CUST1187 | D10: PROD99 | E10: STORE5 | F10: 2.4796175 | G10: 448.25 | H10: 0.07 | I10: PayPal | J10: 1250.6175 | K10: Dr. Suzanne Bullock | L10: 42 | M10: Male | N10: Lake Blaketon | O10: Alabama | P10: USA | Q10: Platinum | R10: Stainless Steel Cookware Set | S10: Home | T10: Kitchen | U10: Campbell Ltd | V10: Gray Ltd | W10: North | X10: Outlet
A11: SALE9 | B11: 45869 | C11: CUST1464 | D11: PROD33 | E11: STORE0 | F11: 2 | G11: 873.17 | H11: 0.23 | I11: PayPal | J11: 1344.6818 | K11: David Pierce | L11: 28 | M11: Female | N11: Grayland | O11: Washington | P11: USA | Q11: Platinum | R11: Modern Wall Clock | S11: Home | T11: Decor | U11: Weiss-Watson | V11: Rivera-Warner | W11: East | X11: Flagship
A12: SALE10 | B12: 45335 | C12: CUST1065 | D12: PROD24 | E12: STORE14 | F12: 1 | G12: 278.63 | H12: 0.07 | I12: Credit Card | J12: 259.1259 | K12: Michael Thomas | L12: 27 | M12: Female | N12: Woodmouth | O12: Nevada | P12: USA | Q12: Silver | R12: Foldable Camping Chair | S12: Sports | T12: Outdoor | U12: Cook Ltd | V12: Martinez, Adkins and Johnson | W12: North | X12: Flagship
A13: SALE11 | B13: 45801 | C13: CUST1320 | D13: PROD39 | E13: STORE1 | F13: 4 | G13: 286.92 | H13: 0.17 | I13: Credit Card | J13: 952.5744 | K13: Jessica Gonzalez | L13: 21 | M13: Female | N13: South Darrenland | O13: Iowa | P13: USA | Q13: Bronze | R13: Portable Power Bank | S13: Electronics | T13: Mobile | U13: Cummings and Sons | V13: Martinez, Adkins and Johnson | W13: North | X13: Flagship
... A2001: SALE1999 | B2001: 45267 | C2001: CUST1023 | D2001: PROD76 | E2001: STORE19 | F2001: 3 | G2001: 68.45 | H2001: 0.17 | I2001: PayPal | J2001: 170.4405 | K2001: Jonathan Steele | L2001: 40 | M2001: Male | N2001: Molinabury | O2001: Oregon | P2001: USA | Q2001: Silver | R2001: Wireless Mouse | S2001: Electronics | T2001: Computer | U2001: Larson Ltd | V2001: Martinez, Adkins and Johnson | W2001: North | X2001: Flagship

Sheet Analysis
D4: Total No of Sales | E4: =COUNT(Table7[Total_Amount]) -> 2000
D5: Male Sales Count | E5: =COUNTIF(Table7[Gender],"Male") -> 968
D6: Female Sales Count | E6: =COUNTIF(Table7[Gender],"Female") -> 1032
D7: Total Sales Amount | E7: =SUM(Table7[Total_Amount]) -> 2175265

Sheet pivot Tables 
A1: Name | B1: Order_Date | C1: Total_Amount | D1: Payment_Type | E1: Age | F1: Gender | G1: Category | H1: Region | L1: Order_Date | M1: Total_Amount | R1: Payment_Type | S1: Total_Amount | W1: Gender | X1: Category | Y1: Total_Amount | AF1: Total_Amount | AG1: Region
A2: Sarah Smith | B2: 45480 | C2: 198.4164 | D2: Credit Card | E2: 48 | F2: Female | G2: Sports | H2: North | L2: 45480 | M2: 198.4164 | O2: Row Labels | P2: Sum of Total_Amount | R2: Credit Card | S2: 198.4164 | W2: Female | X2: Sports | Y2: 198.4164 | AF2: 198.4164 | AG2: North
A3: Michael Foley | B3: 45285 | C3: 228.7893 | D3: PayPal | E3: 45 | F3: Male | G3: Electronics | H3: North | L3: 45285 | M3: 228.7893 | O3: 2023 | P3: 224167.89 | R3: PayPal | S3: 228.7893 | T3: Row Labels | U3: Sum of Total_Amount | W3: Male | X3: Electronics | Y3: 228.7893 | Z3: Sum of Total_Amount | AA3: Column Labels | AF3: 228.7893 | AG3: North
A4: Christopher Sutton | B4: 45446 | C4: 2742.15 | D4: Credit Card | E4: 43 | F4: Female | G4: Beauty | H4: West | L4: 45446 | M4: 2742.15 | O4: 2024 | P4: 1093875.3 | R4: Credit Card | S4: 2742.15 | T4: COD | U4: 703703.34 | W4: Female | X4: Beauty | Y4: 2742.15 | Z4: Row Labels | AA4: Female | AB4: Male | AC4: Grand Total | AF4: 2742.15 | AG4: West | AH4: Row Labels | AI4: Sum of Total_Amount
A5: John Jordan | B5: 45259 | C5: 774.0684 | D5: COD | E5: 39 | F5: Female | G5: Electronics | H5: West | L5: 45259 | M5: 774.0684 | O5: 2025 | P5: 857221.8 | R5: COD | S5: 774.0684 | T5: Credit Card | U5: 714843.57 | W5: Female | X5: Electronics | Y5: 774.0684 | Z5: Beauty | AA5: 180344.28 | AB5: 175735.69 | AC5: 356079.97 | AF5: 774.0684 | AG5: West | AH5: East | AI5: 199672.35
A6: Amanda Powell | B6: 45297 | C6: 1833.438 | D6: Credit Card | E6: 21 | F6: Male | G6: Beauty | H6: North | L6: 45297 | M6: 1833.438 | O6: Grand Total | P6: 2175265 | R6: Credit Card | S6: 1833.438 | T6: PayPal | U6: 756718.1 | W6: Male | X6: Beauty | Y6: 1833.438 | Z6: Clothing | AA6: 155935.59 | AB6: 166848.67 | AC6: 322784.26 | AF6: 1833.438 | AG6: North | AH6: North | AI6: 1380704.5
A7: Anthony Phillips | B7: 45499 | C7: 357.2343 | D7: COD | E7: 21 | F7: Female | G7: Electronics | H7: South | L7: 45499 | M7: 357.2343 | R7: COD | S7: 357.2343 | T7: Grand Total | U7: 2175265 | W7: Female | X7: Electronics | Y7: 357.2343 | Z7: Electronics | AA7: 281133.04 | AB7: 222031.8 | AC7: 503164.84 | AF7: 357.2343 | AG7: South | AH7: South | AI7: 435916.67
A8: John Scott | B8: 45850 | C8: 1335.027 | D8: PayPal | E8: 60 | F8: Female | G8: Home | H8: South | L8: 45850 | M8: 1335.027 | R8: PayPal | S8: 1335.027 | W8: Female | X8: Home | Y8: 1335.027 | Z8: Home | AA8: 217025.26 | AB8: 231524.56 | AC8: 448549.82 | AF8: 1335.027 | AG8: South | AH8: West | AI8: 158971.46
A9: Patrick Roberts | B9: 45248 | C9: 1054.5612 | D9: PayPal | E9: 31 | F9: Male | G9: Home | H9: West | L9: 45248 | M9: 1054.5612 | R9: PayPal | S9: 1054.5612 | W9: Male | X9: Home | Y9: 1054.5612 | Z9: Sports | AA9: 276719.29 | AB9: 267966.82 | AC9: 544686.11 | AF9: 1054.5612 | AG9: West | AH9: Grand Total | AI9: 2175265
A10: Dr. Suzanne Bullock | B10: 45781 | C10: 1250.6175 | D10: PayPal | E10: 42 | F10: Male | G10: Home | H10: North | L10: 45781 | M10: 1250.6175 | R10: PayPal | S10: 1250.6175 | W10: Male | X10: Home | Y10: 1250.6175 | Z10: Grand Total | AA10: 1111157.5 | AB10: 1064107.5 | AC10: 2175265 | AF10: 1250.6175 | AG10: North
A11: David Pierce | B11: 45869 | C11: 1344.6818 | D11: PayPal | E11: 28 | F11: Female | G11: Home | H11: East | L11: 45869 | M11: 1344.6818 | R11: PayPal | S11: 1344.6818 | W11: Female | X11: Home | Y11: 1344.6818 | AF11: 1344.6818 | AG11: East
A12: Michael Thomas | B12: 45335 | C12: 259.1259 | D12: Credit Card | E12: 27 | F12: Female | G12: Sports | H12: North | L12: 45335 | M12: 259.1259 | R12: Credit Card | S12: 259.1259 | W12: Female | X12: Sports | Y12: 259.1259 | AF12: 259.1259 | AG12: North
A13: Jessica Gonzalez | B13: 45801 | C13: 952.5744 | D13: Credit Card | E13: 21 | F13: Female | G13: Electronics | H13: North | L13: 45801 | M13: 952.5744 | R13: Credit Card | S13: 952.5744 | W13: Female | X13: Electronics | Y13: 952.5744 | AF13: 952.5744 | AG13: North
A14: Wesley Short | B14: 45528 | C14: 2552.5368 | D14: Credit Card | E14: 40 | F14: Male | G14: Sports | H14: South | L14: 45528 | M14: 2552.5368 | R14: Credit Card | S14: 2552.5368 | W14: Male | X14: Sports | Y14: 2552.5368 | AF14: 2552.5368 | AG14: South
A15: Adam Castro | B15: 45875 | C15: 443.66 | D15: PayPal | E15: 19 | F15: Male | G15: Electronics | H15: North | L15: 45875 | M15: 443.66 | R15: PayPal | S15: 443.66 | W15: Male | X15: Electronics | Y15: 443.66 | AF15: 443.66 | AG15: North
A16: Sherry Cabrera | B16: 45829 | C16: 1145.8548 | D16: PayPal | E16: 31 | F16: Male | G16: Sports | H16: North | L16: 45829 | M16: 1145.8548 | R16: PayPal | S16: 1145.8548 | W16: Male | X16: Sports | Y16: 1145.8548 | AF16: 1145.8548 | AG16: North
A17: Lindsay Beasley | B17: 45636 | C17: 2509.4592 | D17: COD | E17: 61 | F17: Male | G17: Clothing | H17: South | L17: 45636 | M17: 2509.4592 | R17: COD | S17: 2509.4592 | W17: Male | X17: Clothing | Y17: 2509.4592 | AF17: 2509.4592 | AG17: South
A18: Arthur Warren | B18: 45913 | C18: 677.97 | D18: Credit Card | E18: 22 | F18: Female | G18: Sports | H18: North | L18: 45913 | M18: 677.97 | R18: Credit Card | S18: 677.97 | W18: Female | X18: Sports | Y18: 677.97 | AF18: 677.97 | AG18: North
A19: Molly Gardner | B19: 45637 | C19: 774.1426 | D19: Credit Card | E19: 61 | F19: Female | G19: Home | H19: South | L19: 45637 | M19: 774.1426 | R19: Credit Card | S19: 774.1426 | W19: Female | X19: Home | Y19: 774.1426 | AF19: 774.1426 | AG19: South
A20: David Patterson | B20: 45517 | C20: 838.845 | D20: COD | E20: 62 | F20: Female | G20: Electronics | H20: South | L20: 45517 | M20: 838.845 | R20: COD | S20: 838.845 | W20: Female | X20: Electronics | Y20: 838.845 | AF20: 838.845 | AG20: South
A21: Maria Hill | B21: 45369 | C21: 1782.4512 | D21: COD | E21: 59 | F21: Female | G21: Beauty | H21: North | L21: 45369 | M21: 1782.4512 | R21: COD | S21: 1782.4512 | W21: Female | X21: Beauty | Y21: 1782.4512 | AF21: 1782.4512 | AG21: North
A22: Justin Cross | B22: 45843 | C22: 2159.4276 | D22: COD | E22: 46 | F22: Male | G22: Sports | H22: North | L22: 45843 | M22: 2159.4276 | R22: COD | S22: 2159.4276 | W22: Male | X22: Sports | Y22: 2159.4276 | AF22: 2159.4276 | AG22: North
... A2001: Jonathan Steele | B2001: 45267 | C2001: 170.4405 | D2001: PayPal | E2001: 40 | F2001: Male | G2001: Electronics | H2001: North | L2001: 45267 | M2001: 170.4405 | R2001: PayPal | S2001: 170.4405 | W2001: Male | X2001: Electronics | Y2001: 170.4405 | AF2001: 170.4405 | AG2001: North

Sheet Dashboard
